Workbook

Sheet Dashboard
A1: CREDIT CARD FLOAT CALCULATOR - ULTIMATE EDITION
A3: NEW: Monthly Bill Tracking + Payment Action Lists
A5: KEY METRICS
A6: Monthly Income: | B6: 4000
A7: Total Active Bills: | B7: 3080
A8: Net After Bills: | B8: =Setup!B4-'Bill Master List'!B33 -> #VALUE!
A10: Total Credit Card Debt: | B10: =SUMIF('Credit Cards'!K3:K17,"Yes",'Credit Cards'!M3:M17) -> 4129.03
A11: Total Credit Available: | B11: 333.61
A12: Overall Utilization: | B12: 0.9259
A14: Active Cards: | B14: 5
A15: Active Bills: | B15: 13
A16: Payoff Strategy: | B16: PayInFull
A19: QUICK START GUIDE:
A21: STEP 1 - SETUP:
A22: • Enter your monthly income and choose your payoff strategy
A24: STEP 2 - CREDIT CARDS:
A25: • Enter all 15 cards with APRs, limits, statement/due/credit report days
A27: STEP 3 - BILL MASTER LIST:
A28: • List all 30 recurring bills
A29: • Assign each bill to a specific card (Card1-Card15)
A31: STEP 4 - 2026 MONTHLY BILLS (NEW!):
A32: • See every month Jan-Dec with bills automatically populated
A33: • Shows EXACTLY which bills hit which cards each month
A34: • Card totals calculated automatically for each month
... A51: 5. Avalanche strategy: Pay minimums + attack highest APR first

Sheet Setup
A1: Credit Card Float & Debt Payoff Calculator - ULTIMATE EDITION
A3: GLOBAL SETTINGS
A4: Setting | B4: Value | C4: Notes
A5: Monthly Take-Home Income | B5: 4000 | C5: Your net income after taxes
A6: Start Year | B6: 2026 | C6: Year for monthly bill tracking
A7: Payoff Strategy | B7: PayInFull | C7: PayInFull or AvalancheExtra
A8: Extra Debt Budget | B8: 0 | C8: Extra $ per month for debt (if Avalanche)
A9: Simulation Months | B9: 36 | C9: How many months to project

Sheet Credit Cards
A1: CREDIT CARDS (Up to 15 Cards)
A2: Card ID | B2: Bank Name | C2: Credit Limit | D2: APR (Annual %) | E2: Statement Day | F2: Due Day | G2: Credit Report Day | H2: Starting Balance | I2: Min Payment % | J2: Min Payment Floor | K2: Active | L2: Cash Advance Balance | M2: Total Current Balance | N2: Cash Advance APR (Annual %) | O2: Cash Advance Fee % | P2: Cash Advance Flat Fee
A3: Card1 | B3: Navy Federal Card | C3: 1500 | D3: 0.18 | E3: 24 | F3: 21 | G3: 24 | H3: 1500.1 | I3: 0.02 | J3: 40 | K3: Yes | L3: 0 | M3: =H3+L3 -> 1500.1 | N3: 18 | O3: 0.05 | P3: 10
A4: Card2 | B4: Indigo 3069 | C4: 500 | D4: 0.359 | E4: 9 | F4: 8 | G4: 9 | H4: 632.81 | I4: 0.02 | J4: 40 | K4: Yes | L4: 0 | M4: =H4+L4 -> 632.81 | N4: 35.9 | O4: 0.05 | P4: 10
A5: Card3 | B5: Indigo 1448 | C5: 1000 | D5: 0.359 | E5: 26 | F5: 25 | G5: 26 | H5: 599.4 | I5: 0.02 | J5: 40 | K5: Yes | L5: 100 | M5: 547.97 | N5: 35.9 | O5: 0.05 | P5: 10
A6: Card4 | B6: Milestone 5093 | C6: 500 | D6: 0.359 | E6: 9 | F6: 8 | G6: 9 | H6: 489.81 | I6: 0.02 | J6: 40 | K6: Yes | L6: 0 | M6: =H6+L6 -> 489.81 | N6: 35.9 | O6: 0.05 | P6: 10
A7: Card5 | B7: Destiny 3992 | C7: 1000 | D7: 0.359 | E7: 26 | F7: 25 | G7: 26 | H7: 944.27 | I7: 0.02 | J7: 40 | K7: Yes | L7: 100 | M7: 958.34 | N7: 35.9 | O7: 0.05 | P7: 10
A8: Card6 | K8: No | M8: =H8+L8 -> 0
A9: Card7 | K9: No | M9: =H9+L9 -> 0
A10: Card8 | K10: No | M10: =H10+L10 -> 0
A11: Card9 | K11: No | M11: =H11+L11 -> 0
A12: Card10 | K12: No | M12: =H12+L12 -> 0
A13: Card11 | K13: No | M13: =H13+L13 -> 0
A14: Card12 | K14: No | M14: =H14+L14 -> 0
A15: Card13 | K15: No | M15: =H15+L15 -> 0
A16: Card14 | K16: No | M16: =H16+L16 -> 0
A17: Card15 | K17: No | M17: =H17+L17 -> 0

Sheet Bill Master List
A1: MONTHLY BILLS MASTER LIST (Up to 30 Bills)
A2: Bill Name | B2: Amount | C2: Due Day | D2: Pay Via | E2: Category | F2: Active | G2: Late Fee | H2: Grace Period (Days) | I2: Late Fee Notes
A3: Storage 1 | B3: 478 | C3: 1 | D3: Card1 | E3: Housing | F3: Yes | G3: 40 | H3: 5 | I3: Lien risk after 30 days late
A4: Storage 2 | B4: 109 | C4: 1 | D4: Card1 | E4: Housing | F4: Yes | G4: 25 | H4: 5 | I4: Lien risk after 30 days late
A5: Storage 3 | B5: 180 | C5: 1 | D5: Card2 | E5: Housing | F5: Yes | G5: 25 | H5: 5 | I5: Lien risk after 30 days late
A6: Storage 4 | B6: 98 | C6: 1 | D6: Card2 | E6: Housing | F6: Yes | G6: 20 | H6: 5 | I6: Lien risk after 30 days late
A7: Intuit | B7: 75 | C7: 20 | D7: Card2 | E7: Utilities | F7: Yes | G7: 0 | H7: 0 | I7: Service suspended if unpaid
A8: Cell Phone | B8: 80 | C8: 5 | D8: Card3 | E8: Phone | F8: Yes | G8: 25 | H8: 0 | I8: Service disconnected after 30 days
A9: Car Payment | B9: 785 | C9: 24 | D9: Card3 | E9: Auto | F9: Yes | G9: 39 | H9: 10 | I9: Repo risk after 60+ days. Hits credit report at 30 days.
A10: Car Insurance | B10: 0 | C10: 10 | D10: Card1 | E10: Auto | F10: Yes | G10: 25 | H10: 10 | I10: Policy cancellation after lapse
A11: Gas/Fuel | B11: 200 | C11: 15 | D11: Card4 | E11: Auto | F11: Yes | G11: 0 | H11: 0 | I11: Variable expense - no late fee
A12: Groceries | B12: 400 | C12: 1 | D12: Card3 | E12: Health | F12: Yes | G12: 0 | H12: 0 | I12: Variable expense - no late fee
A13: Klarna | B13: 45 | C13: 15 | D13: Card2 | E13: Entertainment | F13: Yes | G13: 25 | H13: 0 | I13: Hits credit after 30 days late
A14: Affirm | B14: 30 | C14: 20 | D14: Card5 | E14: Food | F14: Yes | G14: 0 | H14: 0 | I14: No late fee but hits credit at 30 days
A15: NTTA | B15: 600 | C15: 15 | D15: Card5 | E15: Auto | F15: Yes | G15: 25 | H15: 30 | I15: Can block vehicle registration. TxTag balance required.
F16: No
F17: No
F18: No
F19: No
F20: No
F21: No
F22: No
F23: No
F24: No
F25: No
F26: No
F27: No
... F32: No
A33: Total Monthly Bills | B33: =SUMIF(F2:F31,"Yes",B2:B31) -> 3080

Sheet 2026 Monthly Bills
A1: 2026 MONTHLY BILL SCHEDULE
A2: All active bills auto-populate. Includes due dates, late fees, and card assignments.
A4: January 2026
A5: Bill Name | B5: Amount | C5: Due Day | D5: Pay Via (Card) | E5: Category | F5: Late Fee | G5: Grace Days | H5: Late Fee Notes
A19: =IF('Bill Master List'!F16="Yes",'Bill Master List'!A16,"") | B19: =IF('Bill Master List'!F16="Yes",'Bill Master List'!B16,"") | C19: =IF('Bill Master List'!F16="Yes",'Bill Master List'!C16,"") | D19: =IF('Bill Master List'!F16="Yes",'Bill Master List'!D16,"") | E19: =IF('Bill Master List'!F16="Yes",'Bill Master List'!E16,"") | F19: =IF('Bill Master List'!F16="Yes",'Bill Master List'!G16,"") | G19: =IF('Bill Master List'!F16="Yes",'Bill Master List'!H16,"") | H19: =IF('Bill Master List'!F16="Yes",'Bill Master List'!I16,"")
A20: =IF('Bill Master List'!F17="Yes",'Bill Master List'!A17,"") | B20: =IF('Bill Master List'!F17="Yes",'Bill Master List'!B17,"") | C20: =IF('Bill Master List'!F17="Yes",'Bill Master List'!C17,"") | D20: =IF('Bill Master List'!F17="Yes",'Bill Master List'!D17,"") | E20: =IF('Bill Master List'!F17="Yes",'Bill Master List'!E17,"") | F20: =IF('Bill Master List'!F17="Yes",'Bill Master List'!G17,"") | G20: =IF('Bill Master List'!F17="Yes",'Bill Master List'!H17,"") | H20: =IF('Bill Master List'!F17="Yes",'Bill Master List'!I17,"")
A21: =IF('Bill Master List'!F18="Yes",'Bill Master List'!A18,"") | B21: =IF('Bill Master List'!F18="Yes",'Bill Master List'!B18,"") | C21: =IF('Bill Master List'!F18="Yes",'Bill Master List'!C18,"") | D21: =IF('Bill Master List'!F18="Yes",'Bill Master List'!D18,"") | E21: =IF('Bill Master List'!F18="Yes",'Bill Master List'!E18,"") | F21: =IF('Bill Master List'!F18="Yes",'Bill Master List'!G18,"") | G21: =IF('Bill Master List'!F18="Yes",'Bill Master List'!H18,"") | H21: =IF('Bill Master List'!F18="Yes",'Bill Master List'!I18,"")
A22: =IF('Bill Master List'!F19="Yes",'Bill Master List'!A19,"") | B22: =IF('Bill Master List'!F19="Yes",'Bill Master List'!B19,"") | C22: =IF('Bill Master List'!F19="Yes",'Bill Master List'!C19,"") | D22: =IF('Bill Master List'!F19="Yes",'Bill Master List'!D19,"") | E22: =IF('Bill Master List'!F19="Yes",'Bill Master List'!E19,"") | F22: =IF('Bill Master List'!F19="Yes",'Bill Master List'!G19,"") | G22: =IF('Bill Master List'!F19="Yes",'Bill Master List'!H19,"") | H22: =IF('Bill Master List'!F19="Yes",'Bill Master List'!I19,"")
A23: =IF('Bill Master List'!F20="Yes",'Bill Master List'!A20,"") | B23: =IF('Bill Master List'!F20="Yes",'Bill Master List'!B20,"") | C23: =IF('Bill Master List'!F20="Yes",'Bill Master List'!C20,"") | D23: =IF('Bill Master List'!F20="Yes",'Bill Master List'!D20,"") | E23: =IF('Bill Master List'!F20="Yes",'Bill Master List'!E20,"") | F23: =IF('Bill Master List'!F20="Yes",'Bill Master List'!G20,"") | G23: =IF('Bill Master List'!F20="Yes",'Bill Master List'!H20,"") | H23: =IF('Bill Master List'!F20="Yes",'Bill Master List'!I20,"")
A24: =IF('Bill Master List'!F21="Yes",'Bill Master List'!A21,"") | B24: =IF('Bill Master List'!F21="Yes",'Bill Master List'!B21,"") | C24: =IF('Bill Master List'!F21="Yes",'Bill Master List'!C21,"") | D24: =IF('Bill Master List'!F21="Yes",'Bill Master List'!D21,"") | E24: =IF('Bill Master List'!F21="Yes",'Bill Master List'!E21,"") | F24: =IF('Bill Master List'!F21="Yes",'Bill Master List'!G21,"") | G24: =IF('Bill Master List'!F21="Yes",'Bill Master List'!H21,"") | H24: =IF('Bill Master List'!F21="Yes",'Bill Master List'!I21,"")
A25: =IF('Bill Master List'!F22="Yes",'Bill Master List'!A22,"") | B25: =IF('Bill Master List'!F22="Yes",'Bill Master List'!B22,"") | C25: =IF('Bill Master List'!F22="Yes",'Bill Master List'!C22,"") | D25: =IF('Bill Master List'!F22="Yes",'Bill Master List'!D22,"") | E25: =IF('Bill Master List'!F22="Yes",'Bill Master List'!E22,"") | F25: =IF('Bill Master List'!F22="Yes",'Bill Master List'!G22,"") | G25: =IF('Bill Master List'!F22="Yes",'Bill Master List'!H22,"") | H25: =IF('Bill Master List'!F22="Yes",'Bill Master List'!I22,"")
A26: =IF('Bill Master List'!F23="Yes",'Bill Master List'!A23,"") | B26: =IF('Bill Master List'!F23="Yes",'Bill Master List'!B23,"") | C26: =IF('Bill Master List'!F23="Yes",'Bill Master List'!C23,"") | D26: =IF('Bill Master List'!F23="Yes",'Bill Master List'!D23,"") | E26: =IF('Bill Master List'!F23="Yes",'Bill Master List'!E23,"") | F26: =IF('Bill Master List'!F23="Yes",'Bill Master List'!G23,"") | G26: =IF('Bill Master List'!F23="Yes",'Bill Master List'!H23,"") | H26: =IF('Bill Master List'!F23="Yes",'Bill Master List'!I23,"")
A27: =IF('Bill Master List'!F24="Yes",'Bill Master List'!A24,"") | B27: =IF('Bill Master List'!F24="Yes",'Bill Master List'!B24,"") | C27: =IF('Bill Master List'!F24="Yes",'Bill Master List'!C24,"") | D27: =IF('Bill Master List'!F24="Yes",'Bill Master List'!D24,"") | E27: =IF('Bill Master List'!F24="Yes",'Bill Master List'!E24,"") | F27: =IF('Bill Master List'!F24="Yes",'Bill Master List'!G24,"") | G27: =IF('Bill Master List'!F24="Yes",'Bill Master List'!H24,"") | H27: =IF('Bill Master List'!F24="Yes",'Bill Master List'!I24,"")
A28: =IF('Bill Master List'!F25="Yes",'Bill Master List'!A25,"") | B28: =IF('Bill Master List'!F25="Yes",'Bill Master List'!B25,"") | C28: =IF('Bill Master List'!F25="Yes",'Bill Master List'!C25,"") | D28: =IF('Bill Master List'!F25="Yes",'Bill Master List'!D25,"") | E28: =IF('Bill Master List'!F25="Yes",'Bill Master List'!E25,"") | F28: =IF('Bill Master List'!F25="Yes",'Bill Master List'!G25,"") | G28: =IF('Bill Master List'!F25="Yes",'Bill Master List'!H25,"") | H28: =IF('Bill Master List'!F25="Yes",'Bill Master List'!I25,"")
A29: =IF('Bill Master List'!F26="Yes",'Bill Master List'!A26,"") | B29: =IF('Bill Master List'!F26="Yes",'Bill Master List'!B26,"") | C29: =IF('Bill Master List'!F26="Yes",'Bill Master List'!C26,"") | D29: =IF('Bill Master List'!F26="Yes",'Bill Master List'!D26,"") | E29: =IF('Bill Master List'!F26="Yes",'Bill Master List'!E26,"") | F29: =IF('Bill Master List'!F26="Yes",'Bill Master List'!G26,"") | G29: =IF('Bill Master List'!F26="Yes",'Bill Master List'!H26,"") | H29: =IF('Bill Master List'!F26="Yes",'Bill Master List'!I26,"")
A30: =IF('Bill Master List'!F27="Yes",'Bill Master List'!A27,"") | B30: =IF('Bill Master List'!F27="Yes",'Bill Master List'!B27,"") | C30: =IF('Bill Master List'!F27="Yes",'Bill Master List'!C27,"") | D30: =IF('Bill Master List'!F27="Yes",'Bill Master List'!D27,"") | E30: =IF('Bill Master List'!F27="Yes",'Bill Master List'!E27,"") | F30: =IF('Bill Master List'!F27="Yes",'Bill Master List'!G27,"") | G30: =IF('Bill Master List'!F27="Yes",'Bill Master List'!H27,"") | H30: =IF('Bill Master List'!F27="Yes",'Bill Master List'!I27,"")
... A35: =IF('Bill Master List'!F32="Yes",'Bill Master List'!A32,"") | B35: =IF('Bill Master List'!F32="Yes",'Bill Master List'!B32,"") | C35: =IF('Bill Master List'!F32="Yes",'Bill Master List'!C32,"") | D35: =IF('Bill Master List'!F32="Yes",'Bill Master List'!D32,"") | E35: =IF('Bill Master List'!F32="Yes",'Bill Master List'!E32,"") | F35: =IF('Bill Master List'!F32="Yes",'Bill Master List'!G32,"") | G35: =IF('Bill Master List'!F32="Yes",'Bill Master List'!H32,"") | H35: =IF('Bill Master List'!F32="Yes",'Bill Master List'!I32,"")
A36: CARD TOTALS: | B36: Card1: | C36: Card2: | D36: Card3: | E36: Card4: | F36: Card5: | G36: MONTH TOTAL: | H36: Late Fee Risk:
B37: =SUMIF(D6:D35,"Card1",B6:B35) -> 0 | C37: =SUMIF(D6:D35,"Card2",B6:B35) -> 0 | D37: =SUMIF(D6:D35,"Card3",B6:B35) -> 0 | E37: =SUMIF(D6:D35,"Card4",B6:B35) -> 0 | F37: =SUMIF(D6:D35,"Card5",B6:B35) -> 0 | G37: =SUM(B6:B35) -> 0 | H37: =SUM(F6:F35) -> 0
A39: February 2026
A40: Bill Name | B40: Amount | C40: Due Day | D40: Pay Via (Card) | E40: Category | F40: Late Fee | G40: Grace Days | H40: Late Fee Notes
A41: Storage 1 | B41: 478 | C41: 1 | D41: Card1 | E41: Housing | F41: 40 | G41: 5 | H41: Lien risk after 30 days late
A42: Car Payment | B42: 785 | C42: 24 | D42: Card3 | E42: Auto | F42: 39 | G42: 10 | H42: Repo risk after 60+ days. Hits credit report at 30 days.
A54: =IF('Bill Master List'!F16="Yes",'Bill Master List'!A16,"") | B54: =IF('Bill Master List'!F16="Yes",'Bill Master List'!B16,"") | C54: =IF('Bill Master List'!F16="Yes",'Bill Master List'!C16,"") | D54: =IF('Bill Master List'!F16="Yes",'Bill Master List'!D16,"") | E54: =IF('Bill Master List'!F16="Yes",'Bill Master List'!E16,"") | F54: =IF('Bill Master List'!F16="Yes",'Bill Master List'!G16,"") | G54: =IF('Bill Master List'!F16="Yes",'Bill Master List'!H16,"") | H54: =IF('Bill Master List'!F16="Yes",'Bill Master List'!I16,"")
A55: =IF('Bill Master List'!F17="Yes",'Bill Master List'!A17,"") | B55: =IF('Bill Master List'!F17="Yes",'Bill Master List'!B17,"") | C55: =IF('Bill Master List'!F17="Yes",'Bill Master List'!C17,"") | D55: =IF('Bill Master List'!F17="Yes",'Bill Master List'!D17,"") | E55: =IF('Bill Master List'!F17="Yes",'Bill Master List'!E17,"") | F55: =IF('Bill Master List'!F17="Yes",'Bill Master List'!G17,"") | G55: =IF('Bill Master List'!F17="Yes",'Bill Master List'!H17,"") | H55: =IF('Bill Master List'!F17="Yes",'Bill Master List'!I17,"")
A56: =IF('Bill Master List'!F18="Yes",'Bill Master List'!A18,"") | B56: =IF('Bill Master List'!F18="Yes",'Bill Master List'!B18,"") | C56: =IF('Bill Master List'!F18="Yes",'Bill Master List'!C18,"") | D56: =IF('Bill Master List'!F18="Yes",'Bill Master List'!D18,"") | E56: =IF('Bill Master List'!F18="Yes",'Bill Master List'!E18,"") | F56: =IF('Bill Master List'!F18="Yes",'Bill Master List'!G18,"") | G56: =IF('Bill Master List'!F18="Yes",'Bill Master List'!H18,"") | H56: =IF('Bill Master List'!F18="Yes",'Bill Master List'!I18,"")
A57: =IF('Bill Master List'!F19="Yes",'Bill Master List'!A19,"") | B57: =IF('Bill Master List'!F19="Yes",'Bill Master List'!B19,"") | C57: =IF('Bill Master List'!F19="Yes",'Bill Master List'!C19,"") | D57: =IF('Bill Master List'!F19="Yes",'Bill Master List'!D19,"") | E57: =IF('Bill Master List'!F19="Yes",'Bill Master List'!E19,"") | F57: =IF('Bill Master List'!F19="Yes",'Bill Master List'!G19,"") | G57: =IF('Bill Master List'!F19="Yes",'Bill Master List'!H19,"") | H57: =IF('Bill Master List'!F19="Yes",'Bill Master List'!I19,"")
A58: =IF('Bill Master List'!F20="Yes",'Bill Master List'!A20,"") | B58: =IF('Bill Master List'!F20="Yes",'Bill Master List'!B20,"") | C58: =IF('Bill Master List'!F20="Yes",'Bill Master List'!C20,"") | D58: =IF('Bill Master List'!F20="Yes",'Bill Master List'!D20,"") | E58: =IF('Bill Master List'!F20="Yes",'Bill Master List'!E20,"") | F58: =IF('Bill Master List'!F20="Yes",'Bill Master List'!G20,"") | G58: =IF('Bill Master List'!F20="Yes",'Bill Master List'!H20,"") | H58: =IF('Bill Master List'!F20="Yes",'Bill Master List'!I20,"")
A59: =IF('Bill Master List'!F21="Yes",'Bill Master List'!A21,"") | B59: =IF('Bill Master List'!F21="Yes",'Bill Master List'!B21,"") | C59: =IF('Bill Master List'!F21="Yes",'Bill Master List'!C21,"") | D59: =IF('Bill Master List'!F21="Yes",'Bill Master List'!D21,"") | E59: =IF('Bill Master List'!F21="Yes",'Bill Master List'!E21,"") | F59: =IF('Bill Master List'!F21="Yes",'Bill Master List'!G21,"") | G59: =IF('Bill Master List'!F21="Yes",'Bill Master List'!H21,"") | H59: =IF('Bill Master List'!F21="Yes",'Bill Master List'!I21,"")
A60: =IF('Bill Master List'!F22="Yes",'Bill Master List'!A22,"") | B60: =IF('Bill Master List'!F22="Yes",'Bill Master List'!B22,"") | C60: =IF('Bill Master List'!F22="Yes",'Bill Master List'!C22,"") | D60: =IF('Bill Master List'!F22="Yes",'Bill Master List'!D22,"") | E60: =IF('Bill Master List'!F22="Yes",'Bill Master List'!E22,"") | F60: =IF('Bill Master List'!F22="Yes",'Bill Master List'!G22,"") | G60: =IF('Bill Master List'!F22="Yes",'Bill Master List'!H22,"") | H60: =IF('Bill Master List'!F22="Yes",'Bill Master List'!I22,"")
A61: =IF('Bill Master List'!F23="Yes",'Bill Master List'!A23,"") | B61: =IF('Bill Master List'!F23="Yes",'Bill Master List'!B23,"") | C61: =IF('Bill Master List'!F23="Yes",'Bill Master List'!C23,"") | D61: =IF('Bill Master List'!F23="Yes",'Bill Master List'!D23,"") | E61: =IF('Bill Master List'!F23="Yes",'Bill Master List'!E23,"") | F61: =IF('Bill Master List'!F23="Yes",'Bill Master List'!G23,"") | G61: =IF('Bill Master List'!F23="Yes",'Bill Master List'!H23,"") | H61: =IF('Bill Master List'!F23="Yes",'Bill Master List'!I23,"")
A62: =IF('Bill Master List'!F24="Yes",'Bill Master List'!A24,"") | B62: =IF('Bill Master List'!F24="Yes",'Bill Master List'!B24,"") | C62: =IF('Bill Master List'!F24="Yes",'Bill Master List'!C24,"") | D62: =IF('Bill Master List'!F24="Yes",'Bill Master List'!D24,"") | E62: =IF('Bill Master List'!F24="Yes",'Bill Master List'!E24,"") | F62: =IF('Bill Master List'!F24="Yes",'Bill Master List'!G24,"") | G62: =IF('Bill Master List'!F24="Yes",'Bill Master List'!H24,"") | H62: =IF('Bill Master List'!F24="Yes",'Bill Master List'!I24,"")
A63: =IF('Bill Master List'!F25="Yes",'Bill Master List'!A25,"") | B63: =IF('Bill Master List'!F25="Yes",'Bill Master List'!B25,"") | C63: =IF('Bill Master List'!F25="Yes",'Bill Master List'!C25,"") | D63: =IF('Bill Master List'!F25="Yes",'Bill Master List'!D25,"") | E63: =IF('Bill Master List'!F25="Yes",'Bill Master List'!E25,"") | F63: =IF('Bill Master List'!F25="Yes",'Bill Master List'!G25,"") | G63: =IF('Bill Master List'!F25="Yes",'Bill Master List'!H25,"") | H63: =IF('Bill Master List'!F25="Yes",'Bill Master List'!I25,"")
A64: =IF('Bill Master List'!F26="Yes",'Bill Master List'!A26,"") | B64: =IF('Bill Master List'!F26="Yes",'Bill Master List'!B26,"") | C64: =IF('Bill Master List'!F26="Yes",'Bill Master List'!C26,"") | D64: =IF('Bill Master List'!F26="Yes",'Bill Master List'!D26,"") | E64: =IF('Bill Master List'!F26="Yes",'Bill Master List'!E26,"") | F64: =IF('Bill Master List'!F26="Yes",'Bill Master List'!G26,"") | G64: =IF('Bill Master List'!F26="Yes",'Bill Master List'!H26,"") | H64: =IF('Bill Master List'!F26="Yes",'Bill Master List'!I26,"")
A65: =IF('Bill Master List'!F27="Yes",'Bill Master List'!A27,"") | B65: =IF('Bill Master List'!F27="Yes",'Bill Master List'!B27,"") | C65: =IF('Bill Master List'!F27="Yes",'Bill Master List'!C27,"") | D65: =IF('Bill Master List'!F27="Yes",'Bill Master List'!D27,"") | E65: =IF('Bill Master List'!F27="Yes",'Bill Master List'!E27,"") | F65: =IF('Bill Master List'!F27="Yes",'Bill Master List'!G27,"") | G65: =IF('Bill Master List'!F27="Yes",'Bill Master List'!H27,"") | H65: =IF('Bill Master List'!F27="Yes",'Bill Master List'!I27,"")
... A70: =IF('Bill Master List'!F32="Yes",'Bill Master List'!A32,"") | B70: =IF('Bill Master List'!F32="Yes",'Bill Master List'!B32,"") | C70: =IF('Bill Master List'!F32="Yes",'Bill Master List'!C32,"") | D70: =IF('Bill Master List'!F32="Yes",'Bill Master List'!D32,"") | E70: =IF('Bill Master List'!F32="Yes",'Bill Master List'!E32,"") | F70: =IF('Bill Master List'!F32="Yes",'Bill Master List'!G32,"") | G70: =IF('Bill Master List'!F32="Yes",'Bill Master List'!H32,"") | H70: =IF('Bill Master List'!F32="Yes",'Bill Master List'!I32,"")
A71: CARD TOTALS: | B71: Card1: | C71: Card2: | D71: Card3: | E71: Card4: | F71: Card5: | G71: MONTH TOTAL: | H71: Late Fee Risk:
B72: =SUMIF(D41:D70,"Card1",B41:B70) -> 478 | C72: =SUMIF(D41:D70,"Card2",B41:B70) -> 0 | D72: =SUMIF(D41:D70,"Card3",B41:B70) -> 785 | E72: =SUMIF(D41:D70,"Card4",B41:B70) -> 0 | F72: =SUMIF(D41:D70,"Card5",B41:B70) -> 0 | G72: =SUM(B41:B70) -> 1263 | H72: =SUM(F41:F70) -> 79
A74: March 2026
A75: Bill Name | B75: Amount | C75: Due Day | D75: Pay Via (Card) | E75: Category | F75: Late Fee | G75: Grace Days | H75: Late Fee Notes
A76: =IF('Bill Master List'!F3="Yes",'Bill Master List'!A3,"") -> Storage 1 | B76: =IF('Bill Master List'!F3="Yes",'Bill Master List'!B3,"") -> 478 | C76: =IF('Bill Master List'!F3="Yes",'Bill Master List'!C3,"") -> 1 | D76: =IF('Bill Master List'!F3="Yes",'Bill Master List'!D3,"") -> Card1 | E76: =IF('Bill Master List'!F3="Yes",'Bill Master List'!E3,"") -> Housing | F76: =IF('Bill Master List'!F3="Yes",'Bill Master List'!G3,"") -> 40 | G76: =IF('Bill Master List'!F3="Yes",'Bill Master List'!H3,"") -> 5 | H76: =IF('Bill Master List'!F3="Yes",'Bill Master List'!I3,"") -> Lien risk after 30 days late
A77: =IF('Bill Master List'!F4="Yes",'Bill Master List'!A4,"") -> Storage 2 | B77: =IF('Bill Master List'!F4="Yes",'Bill Master List'!B4,"") -> 109 | C77: =IF('Bill Master List'!F4="Yes",'Bill Master List'!C4,"") -> 1 | D77: =IF('Bill Master List'!F4="Yes",'Bill Master List'!D4,"") -> Card1 | E77: =IF('Bill Master List'!F4="Yes",'Bill Master List'!E4,"") -> Housing | F77: =IF('Bill Master List'!F4="Yes",'Bill Master List'!G4,"") -> 25 | G77: =IF('Bill Master List'!F4="Yes",'Bill Master List'!H4,"") -> 5 | H77: =IF('Bill Master List'!F4="Yes",'Bill Master List'!I4,"") -> Lien risk after 30 days late
A78: =IF('Bill Master List'!F5="Yes",'Bill Master List'!A5,"") -> Storage 3 | B78: =IF('Bill Master List'!F5="Yes",'Bill Master List'!B5,"") -> 180 | C78: =IF('Bill Master List'!F5="Yes",'Bill Master List'!C5,"") -> 1 | D78: =IF('Bill Master List'!F5="Yes",'Bill Master List'!D5,"") -> Card2 | E78: =IF('Bill Master List'!F5="Yes",'Bill Master List'!E5,"") -> Housing | F78: =IF('Bill Master List'!F5="Yes",'Bill Master List'!G5,"") -> 25 | G78: =IF('Bill Master List'!F5="Yes",'Bill Master List'!H5,"") -> 5 | H78: =IF('Bill Master List'!F5="Yes",'Bill Master List'!I5,"") -> Lien risk after 30 days late
A79: =IF('Bill Master List'!F6="Yes",'Bill Master List'!A6,"") -> Storage 4 | B79: =IF('Bill Master List'!F6="Yes",'Bill Master List'!B6,"") -> 98 | C79: =IF('Bill Master List'!F6="Yes",'Bill Master List'!C6,"") -> 1 | D79: =IF('Bill Master List'!F6="Yes",'Bill Master List'!D6,"") -> Card2 | E79: =IF('Bill Master List'!F6="Yes",'Bill Master List'!E6,"") -> Housing | F79: =IF('Bill Master List'!F6="Yes",'Bill Master List'!G6,"") -> 20 | G79: =IF('Bill Master List'!F6="Yes",'Bill Master List'!H6,"") -> 5 | H79: =IF('Bill Master List'!F6="Yes",'Bill Master List'!I6,"") -> Lien risk after 30 days late
A80: =IF('Bill Master List'!F7="Yes",'Bill Master List'!A7,"") -> Intuit | B80: =IF('Bill Master List'!F7="Yes",'Bill Master List'!B7,"") -> 75 | C80: =IF('Bill Master List'!F7="Yes",'Bill Master List'!C7,"") -> 20 | D80: =IF('Bill Master List'!F7="Yes",'Bill Master List'!D7,"") -> Card2 | E80: =IF('Bill Master List'!F7="Yes",'Bill Master List'!E7,"") -> Utilities | F80: =IF('Bill Master List'!F7="Yes",'Bill Master List'!G7,"") -> 0 | G80: =IF('Bill Master List'!F7="Yes",'Bill Master List'!H7,"") -> 0 | H80: =IF('Bill Master List'!F7="Yes",'Bill Master List'!I7,"") -> Service suspended if unpaid
A81: =IF('Bill Master List'!F8="Yes",'Bill Master List'!A8,"") -> Cell Phone | B81: =IF('Bill Master List'!F8="Yes",'Bill Master List'!B8,"") -> 80 | C81: =IF('Bill Master List'!F8="Yes",'Bill Master List'!C8,"") -> 5 | D81: =IF('Bill Master List'!F8="Yes",'Bill Master List'!D8,"") -> Card3 | E81: =IF('Bill Master List'!F8="Yes",'Bill Master List'!E8,"") -> Phone | F81: =IF('Bill Master List'!F8="Yes",'Bill Master List'!G8,"") -> 25 | G81: =IF('Bill Master List'!F8="Yes",'Bill Master List'!H8,"") -> 0 | H81: =IF('Bill Master List'!F8="Yes",'Bill Master List'!I8,"") -> Service disconnected after 30 days
A82: =IF('Bill Master List'!F9="Yes",'Bill Master List'!A9,"") -> Car Payment | B82: =IF('Bill Master List'!F9="Yes",'Bill Master List'!B9,"") -> 785 | C82: =IF('Bill Master List'!F9="Yes",'Bill Master List'!C9,"") -> 24 | D82: =IF('Bill Master List'!F9="Yes",'Bill Master List'!D9,"") -> Card3 | E82: =IF('Bill Master List'!F9="Yes",'Bill Master List'!E9,"") -> Auto | F82: =IF('Bill Master List'!F9="Yes",'Bill Master List'!G9,"") -> 39 | G82: =IF('Bill Master List'!F9="Yes",'Bill Master List'!H9,"") -> 10 | H82: =IF('Bill Master List'!F9="Yes",'Bill Master List'!I9,"") -> Repo risk after 60+ days. Hits credit report at 30 days.
A83: =IF('Bill Master List'!F10="Yes",'Bill Master List'!A10,"") -> Car Insurance | B83: =IF('Bill Master List'!F10="Yes",'Bill Master List'!B10,"") -> 0 | C83: =IF('Bill Master List'!F10="Yes",'Bill Master List'!C10,"") -> 10 | D83: =IF('Bill Master List'!F10="Yes",'Bill Master List'!D10,"") -> Card1 | E83: =IF('Bill Master List'!F10="Yes",'Bill Master List'!E10,"") -> Auto | F83: =IF('Bill Master List'!F10="Yes",'Bill Master List'!G10,"") -> 25 | G83: =IF('Bill Master List'!F10="Yes",'Bill Master List'!H10,"") -> 10 | H83: =IF('Bill Master List'!F10="Yes",'Bill Master List'!I10,"") -> Policy cancellation after lapse
A84: =IF('Bill Master List'!F11="Yes",'Bill Master List'!A11,"") -> Gas/Fuel | B84: =IF('Bill Master List'!F11="Yes",'Bill Master List'!B11,"") -> 200 | C84: =IF('Bill Master List'!F11="Yes",'Bill Master List'!C11,"") -> 15 | D84: =IF('Bill Master List'!F11="Yes",'Bill Master List'!D11,"") -> Card4 | E84: =IF('Bill Master List'!F11="Yes",'Bill Master List'!E11,"") -> Auto | F84: =IF('Bill Master List'!F11="Yes",'Bill Master List'!G11,"") -> 0 | G84: =IF('Bill Master List'!F11="Yes",'Bill Master List'!H11,"") -> 0 | H84: =IF('Bill Master List'!F11="Yes",'Bill Master List'!I11,"") -> Variable expense - no late fee
A85: =IF('Bill Master List'!F12="Yes",'Bill Master List'!A12,"") -> Groceries | B85: =IF('Bill Master List'!F12="Yes",'Bill Master List'!B12,"") -> 400 | C85: =IF('Bill Master List'!F12="Yes",'Bill Master List'!C12,"") -> 1 | D85: =IF('Bill Master List'!F12="Yes",'Bill Master List'!D12,"") -> Card3 | E85: =IF('Bill Master List'!F12="Yes",'Bill Master List'!E12,"") -> Health | F85: =IF('Bill Master List'!F12="Yes",'Bill Master List'!G12,"") -> 0 | G85: =IF('Bill Master List'!F12="Yes",'Bill Master List'!H12,"") -> 0 | H85: =IF('Bill Master List'!F12="Yes",'Bill Master List'!I12,"") -> Variable expense - no late fee
A86: =IF('Bill Master List'!F13="Yes",'Bill Master List'!A13,"") -> Klarna | B86: =IF('Bill Master List'!F13="Yes",'Bill Master List'!B13,"") -> 45 | C86: =IF('Bill Master List'!F13="Yes",'Bill Master List'!C13,"") -> 15 | D86: =IF('Bill Master List'!F13="Yes",'Bill Master List'!D13,"") -> Card2 | E86: =IF('Bill Master List'!F13="Yes",'Bill Master List'!E13,"") -> Entertainment | F86: =IF('Bill Master List'!F13="Yes",'Bill Master List'!G13,"") -> 25 | G86: =IF('Bill Master List'!F13="Yes",'Bill Master List'!H13,"") -> 0 | H86: =IF('Bill Master List'!F13="Yes",'Bill Master List'!I13,"") -> Hits credit after 30 days late
A87: =IF('Bill Master List'!F14="Yes",'Bill Master List'!A14,"") -> Affirm | B87: =IF('Bill Master List'!F14="Yes",'Bill Master List'!B14,"") -> 30 | C87: =IF('Bill Master List'!F14="Yes",'Bill Master List'!C14,"") -> 20 | D87: =IF('Bill Master List'!F14="Yes",'Bill Master List'!D14,"") -> Card5 | E87: =IF('Bill Master List'!F14="Yes",'Bill Master List'!E14,"") -> Food | F87: =IF('Bill Master List'!F14="Yes",'Bill Master List'!G14,"") -> 0 | G87: =IF('Bill Master List'!F14="Yes",'Bill Master List'!H14,"") -> 0 | H87: =IF('Bill Master List'!F14="Yes",'Bill Master List'!I14,"") -> No late fee but hits credit at 30 days
... A105: =IF('Bill Master List'!F32="Yes",'Bill Master List'!A32,"") | B105: =IF('Bill Master List'!F32="Yes",'Bill Master List'!B32,"") | C105: =IF('Bill Master List'!F32="Yes",'Bill Master List'!C32,"") | D105: =IF('Bill Master List'!F32="Yes",'Bill Master List'!D32,"") | E105: =IF('Bill Master List'!F32="Yes",'Bill Master List'!E32,"") | F105: =IF('Bill Master List'!F32="Yes",'Bill Master List'!G32,"") | G105: =IF('Bill Master List'!F32="Yes",'Bill Master List'!H32,"") | H105: =IF('Bill Master List'!F32="Yes",'Bill Master List'!I32,"")
A106: CARD TOTALS: | B106: Card1: | C106: Card2: | D106: Card3: | E106: Card4: | F106: Card5: | G106: MONTH TOTAL: | H106: Late Fee Risk:
B107: =SUMIF(D76:D105,"Card1",B76:B105) -> 587 | C107: =SUMIF(D76:D105,"Card2",B76:B105) -> 398 | D107: =SUMIF(D76:D105,"Card3",B76:B105) -> 1265 | E107: =SUMIF(D76:D105,"Card4",B76:B105) -> 200 | F107: =SUMIF(D76:D105,"Card5",B76:B105) -> 630 | G107: =SUM(B76:B105) -> 3080 | H107: =SUM(F76:F105) -> 249
A109: April 2026
A110: Bill Name | B110: Amount | C110: Due Day | D110: Pay Via (Card) | E110: Category | F110: Late Fee | G110: Grace Days | H110: Late Fee Notes
A111: =IF('Bill Master List'!F3="Yes",'Bill Master List'!A3,"") -> Storage 1 | B111: =IF('Bill Master List'!F3="Yes",'Bill Master List'!B3,"") -> 478 | C111: =IF('Bill Master List'!F3="Yes",'Bill Master List'!C3,"") -> 1 | D111: =IF('Bill Master List'!F3="Yes",'Bill Master List'!D3,"") -> Card1 | E111: =IF('Bill Master List'!F3="Yes",'Bill Master List'!E3,"") -> Housing | F111: =IF('Bill Master List'!F3="Yes",'Bill Master List'!G3,"") -> 40 | G111: =IF('Bill Master List'!F3="Yes",'Bill Master List'!H3,"") -> 5 | H111: =IF('Bill Master List'!F3="Yes",'Bill Master List'!I3,"") -> Lien risk after 30 days late
A112: =IF('Bill Master List'!F4="Yes",'Bill Master List'!A4,"") -> Storage 2 | B112: =IF('Bill Master List'!F4="Yes",'Bill Master List'!B4,"") -> 109 | C112: =IF('Bill Master List'!F4="Yes",'Bill Master List'!C4,"") -> 1 | D112: =IF('Bill Master List'!F4="Yes",'Bill Master List'!D4,"") -> Card1 | E112: =IF('Bill Master List'!F4="Yes",'Bill Master List'!E4,"") -> Housing | F112: =IF('Bill Master List'!F4="Yes",'Bill Master List'!G4,"") -> 25 | G112: =IF('Bill Master List'!F4="Yes",'Bill Master List'!H4,"") -> 5 | H112: =IF('Bill Master List'!F4="Yes",'Bill Master List'!I4,"") -> Lien risk after 30 days late
A113: =IF('Bill Master List'!F5="Yes",'Bill Master List'!A5,"") -> Storage 3 | B113: =IF('Bill Master List'!F5="Yes",'Bill Master List'!B5,"") -> 180 | C113: =IF('Bill Master List'!F5="Yes",'Bill Master List'!C5,"") -> 1 | D113: =IF('Bill Master List'!F5="Yes",'Bill Master List'!D5,"") -> Card2 | E113: =IF('Bill Master List'!F5="Yes",'Bill Master List'!E5,"") -> Housing | F113: =IF('Bill Master List'!F5="Yes",'Bill Master List'!G5,"") -> 25 | G113: =IF('Bill Master List'!F5="Yes",'Bill Master List'!H5,"") -> 5 | H113: =IF('Bill Master List'!F5="Yes",'Bill Master List'!I5,"") -> Lien risk after 30 days late
A114: =IF('Bill Master List'!F6="Yes",'Bill Master List'!A6,"") -> Storage 4 | B114: =IF('Bill Master List'!F6="Yes",'Bill Master List'!B6,"") -> 98 | C114: =IF('Bill Master List'!F6="Yes",'Bill Master List'!C6,"") -> 1 | D114: =IF('Bill Master List'!F6="Yes",'Bill Master List'!D6,"") -> Card2 | E114: =IF('Bill Master List'!F6="Yes",'Bill Master List'!E6,"") -> Housing | F114: =IF('Bill Master List'!F6="Yes",'Bill Master List'!G6,"") -> 20 | G114: =IF('Bill Master List'!F6="Yes",'Bill Master List'!H6,"") -> 5 | H114: =IF('Bill Master List'!F6="Yes",'Bill Master List'!I6,"") -> Lien risk after 30 days late
A115: =IF('Bill Master List'!F7="Yes",'Bill Master List'!A7,"") -> Intuit | B115: =IF('Bill Master List'!F7="Yes",'Bill Master List'!B7,"") -> 75 | C115: =IF('Bill Master List'!F7="Yes",'Bill Master List'!C7,"") -> 20 | D115: =IF('Bill Master List'!F7="Yes",'Bill Master List'!D7,"") -> Card2 | E115: =IF('Bill Master List'!F7="Yes",'Bill Master List'!E7,"") -> Utilities | F115: =IF('Bill Master List'!F7="Yes",'Bill Master List'!G7,"") -> 0 | G115: =IF('Bill Master List'!F7="Yes",'Bill Master List'!H7,"") -> 0 | H115: =IF('Bill Master List'!F7="Yes",'Bill Master List'!I7,"") -> Service suspended if unpaid
A116: =IF('Bill Master List'!F8="Yes",'Bill Master List'!A8,"") -> Cell Phone | B116: =IF('Bill Master List'!F8="Yes",'Bill Master List'!B8,"") -> 80 | C116: =IF('Bill Master List'!F8="Yes",'Bill Master List'!C8,"") -> 5 | D116: =IF('Bill Master List'!F8="Yes",'Bill Master List'!D8,"") -> Card3 | E116: =IF('Bill Master List'!F8="Yes",'Bill Master List'!E8,"") -> Phone | F116: =IF('Bill Master List'!F8="Yes",'Bill Master List'!G8,"") -> 25 | G116: =IF('Bill Master List'!F8="Yes",'Bill Master List'!H8,"") -> 0 | H116: =IF('Bill Master List'!F8="Yes",'Bill Master List'!I8,"") -> Service disconnected after 30 days
A117: =IF('Bill Master List'!F9="Yes",'Bill Master List'!A9,"") -> Car Payment | B117: =IF('Bill Master List'!F9="Yes",'Bill Master List'!B9,"") -> 785 | C117: =IF('Bill Master List'!F9="Yes",'Bill Master List'!C9,"") -> 24 | D117: =IF('Bill Master List'!F9="Yes",'Bill Master List'!D9,"") -> Card3 | E117: =IF('Bill Master List'!F9="Yes",'Bill Master List'!E9,"") -> Auto | F117: =IF('Bill Master List'!F9="Yes",'Bill Master List'!G9,"") -> 39 | G117: =IF('Bill Master List'!F9="Yes",'Bill Master List'!H9,"") -> 10 | H117: =IF('Bill Master List'!F9="Yes",'Bill Master List'!I9,"") -> Repo risk after 60+ days. Hits credit report at 30 days.
A118: =IF('Bill Master List'!F10="Yes",'Bill Master List'!A10,"") -> Car Insurance | B118: =IF('Bill Master List'!F10="Yes",'Bill Master List'!B10,"") -> 0 | C118: =IF('Bill Master List'!F10="Yes",'Bill Master List'!C10,"") -> 10 | D118: =IF('Bill Master List'!F10="Yes",'Bill Master List'!D10,"") -> Card1 | E118: =IF('Bill Master List'!F10="Yes",'Bill Master List'!E10,"") -> Auto | F118: =IF('Bill Master List'!F10="Yes",'Bill Master List'!G10,"") -> 25 | G118: =IF('Bill Master List'!F10="Yes",'Bill Master List'!H10,"") -> 10 | H118: =IF('Bill Master List'!F10="Yes",'Bill Master List'!I10,"") -> Policy cancellation after lapse
A119: =IF('Bill Master List'!F11="Yes",'Bill Master List'!A11,"") -> Gas/Fuel | B119: =IF('Bill Master List'!F11="Yes",'Bill Master List'!B11,"") -> 200 | C119: =IF('Bill Master List'!F11="Yes",'Bill Master List'!C11,"") -> 15 | D119: =IF('Bill Master List'!F11="Yes",'Bill Master List'!D11,"") -> Card4 | E119: =IF('Bill Master List'!F11="Yes",'Bill Master List'!E11,"") -> Auto | F119: =IF('Bill Master List'!F11="Yes",'Bill Master List'!G11,"") -> 0 | G119: =IF('Bill Master List'!F11="Yes",'Bill Master List'!H11,"") -> 0 | H119: =IF('Bill Master List'!F11="Yes",'Bill Master List'!I11,"") -> Variable expense - no late fee
A120: =IF('Bill Master List'!F12="Yes",'Bill Master List'!A12,"") -> Groceries | B120: =IF('Bill Master List'!F12="Yes",'Bill Master List'!B12,"") -> 400 | C120: =IF('Bill Master List'!F12="Yes",'Bill Master List'!C12,"") -> 1 | D120: =IF('Bill Master List'!F12="Yes",'Bill Master List'!D12,"") -> Card3 | E120: =IF('Bill Master List'!F12="Yes",'Bill Master List'!E12,"") -> Health | F120: =IF('Bill Master List'!F12="Yes",'Bill Master List'!G12,"") -> 0 | G120: =IF('Bill Master List'!F12="Yes",'Bill Master List'!H12,"") -> 0 | H120: =IF('Bill Master List'!F12="Yes",'Bill Master List'!I12,"") -> Variable expense - no late fee
A121: =IF('Bill Master List'!F13="Yes",'Bill Master List'!A13,"") -> Klarna | B121: =IF('Bill Master List'!F13="Yes",'Bill Master List'!B13,"") -> 45 | C121: =IF('Bill Master List'!F13="Yes",'Bill Master List'!C13,"") -> 15 | D121: =IF('Bill Master List'!F13="Yes",'Bill Master List'!D13,"") -> Card2 | E121: =IF('Bill Master List'!F13="Yes",'Bill Master List'!E13,"") -> Entertainment | F121: =IF('Bill Master List'!F13="Yes",'Bill Master List'!G13,"") -> 25 | G121: =IF('Bill Master List'!F13="Yes",'Bill Master List'!H13,"") -> 0 | H121: =IF('Bill Master List'!F13="Yes",'Bill Master List'!I13,"") -> Hits credit after 30 days late
A122: =IF('Bill Master List'!F14="Yes",'Bill Master List'!A14,"") -> Affirm | B122: =IF('Bill Master List'!F14="Yes",'Bill Master List'!B14,"") -> 30 | C122: =IF('Bill Master List'!F14="Yes",'Bill Master List'!C14,"") -> 20 | D122: =IF('Bill Master List'!F14="Yes",'Bill Master List'!D14,"") -> Card5 | E122: =IF('Bill Master List'!F14="Yes",'Bill Master List'!E14,"") -> Food | F122: =IF('Bill Master List'!F14="Yes",'Bill Master List'!G14,"") -> 0 | G122: =IF('Bill Master List'!F14="Yes",'Bill Master List'!H14,"") -> 0 | H122: =IF('Bill Master List'!F14="Yes",'Bill Master List'!I14,"") -> No late fee but hits credit at 30 days
... A140: =IF('Bill Master List'!F32="Yes",'Bill Master List'!A32,"") | B140: =IF('Bill Master List'!F32="Yes",'Bill Master List'!B32,"") | C140: =IF('Bill Master List'!F32="Yes",'Bill Master List'!C32,"") | D140: =IF('Bill Master List'!F32="Yes",'Bill Master List'!D32,"") | E140: =IF('Bill Master List'!F32="Yes",'Bill Master List'!E32,"") | F140: =IF('Bill Master List'!F32="Yes",'Bill Master List'!G32,"") | G140: =IF('Bill Master List'!F32="Yes",'Bill Master List'!H32,"") | H140: =IF('Bill Master List'!F32="Yes",'Bill Master List'!I32,"")
A141: CARD TOTALS: | B141: Card1: | C141: Card2: | D141: Card3: | E141: Card4: | F141: Card5: | G141: MONTH TOTAL: | H141: Late Fee Risk:
B142: =SUMIF(D111:D140,"Card1",B111:B140) -> 587 | C142: =SUMIF(D111:D140,"Card2",B111:B140) -> 398 | D142: =SUMIF(D111:D140,"Card3",B111:B140) -> 1265 | E142: =SUMIF(D111:D140,"Card4",B111:B140) -> 200 | F142: =SUMIF(D111:D140,"Card5",B111:B140) -> 630 | G142: =SUM(B111:B140) -> 3080 | H142: =SUM(F111:F140) -> 249
A144: May 2026
A145: Bill Name | B145: Amount | C145: Due Day | D145: Pay Via (Card) | E145: Category | F145: Late Fee | G145: Grace Days | H145: Late Fee Notes
A146: =IF('Bill Master List'!F3="Yes",'Bill Master List'!A3,"") -> Storage 1 | B146: =IF('Bill Master List'!F3="Yes",'Bill Master List'!B3,"") -> 478 | C146: =IF('Bill Master List'!F3="Yes",'Bill Master List'!C3,"") -> 1 | D146: =IF('Bill Master List'!F3="Yes",'Bill Master List'!D3,"") -> Card1 | E146: =IF('Bill Master List'!F3="Yes",'Bill Master List'!E3,"") -> Housing | F146: =IF('Bill Master List'!F3="Yes",'Bill Master List'!G3,"") -> 40 | G146: =IF('Bill Master List'!F3="Yes",'Bill Master List'!H3,"") -> 5 | H146: =IF('Bill Master List'!F3="Yes",'Bill Master List'!I3,"") -> Lien risk after 30 days late
A147: =IF('Bill Master List'!F4="Yes",'Bill Master List'!A4,"") -> Storage 2 | B147: =IF('Bill Master List'!F4="Yes",'Bill Master List'!B4,"") -> 109 | C147: =IF('Bill Master List'!F4="Yes",'Bill Master List'!C4,"") -> 1 | D147: =IF('Bill Master List'!F4="Yes",'Bill Master List'!D4,"") -> Card1 | E147: =IF('Bill Master List'!F4="Yes",'Bill Master List'!E4,"") -> Housing | F147: =IF('Bill Master List'!F4="Yes",'Bill Master List'!G4,"") -> 25 | G147: =IF('Bill Master List'!F4="Yes",'Bill Master List'!H4,"") -> 5 | H147: =IF('Bill Master List'!F4="Yes",'Bill Master List'!I4,"") -> Lien risk after 30 days late
A148: =IF('Bill Master List'!F5="Yes",'Bill Master List'!A5,"") -> Storage 3 | B148: =IF('Bill Master List'!F5="Yes",'Bill Master List'!B5,"") -> 180 | C148: =IF('Bill Master List'!F5="Yes",'Bill Master List'!C5,"") -> 1 | D148: =IF('Bill Master List'!F5="Yes",'Bill Master List'!D5,"") -> Card2 | E148: =IF('Bill Master List'!F5="Yes",'Bill Master List'!E5,"") -> Housing | F148: =IF('Bill Master List'!F5="Yes",'Bill Master List'!G5,"") -> 25 | G148: =IF('Bill Master List'!F5="Yes",'Bill Master List'!H5,"") -> 5 | H148: =IF('Bill Master List'!F5="Yes",'Bill Master List'!I5,"") -> Lien risk after 30 days late
A149: =IF('Bill Master List'!F6="Yes",'Bill Master List'!A6,"") -> Storage 4 | B149: =IF('Bill Master List'!F6="Yes",'Bill Master List'!B6,"") -> 98 | C149: =IF('Bill Master List'!F6="Yes",'Bill Master List'!C6,"") -> 1 | D149: =IF('Bill Master List'!F6="Yes",'Bill Master List'!D6,"") -> Card2 | E149: =IF('Bill Master List'!F6="Yes",'Bill Master List'!E6,"") -> Housing | F149: =IF('Bill Master List'!F6="Yes",'Bill Master List'!G6,"") -> 20 | G149: =IF('Bill Master List'!F6="Yes",'Bill Master List'!H6,"") -> 5 | H149: =IF('Bill Master List'!F6="Yes",'Bill Master List'!I6,"") -> Lien risk after 30 days late
A150: =IF('Bill Master List'!F7="Yes",'Bill Master List'!A7,"") -> Intuit | B150: =IF('Bill Master List'!F7="Yes",'Bill Master List'!B7,"") -> 75 | C150: =IF('Bill Master List'!F7="Yes",'Bill Master List'!C7,"") -> 20 | D150: =IF('Bill Master List'!F7="Yes",'Bill Master List'!D7,"") -> Card2 | E150: =IF('Bill Master List'!F7="Yes",'Bill Master List'!E7,"") -> Utilities | F150: =IF('Bill Master List'!F7="Yes",'Bill Master List'!G7,"") -> 0 | G150: =IF('Bill Master List'!F7="Yes",'Bill Master List'!H7,"") -> 0 | H150: =IF('Bill Master List'!F7="Yes",'Bill Master List'!I7,"") -> Service suspended if unpaid
A151: =IF('Bill Master List'!F8="Yes",'Bill Master List'!A8,"") -> Cell Phone | B151: =IF('Bill Master List'!F8="Yes",'Bill Master List'!B8,"") -> 80 | C151: =IF('Bill Master List'!F8="Yes",'Bill Master List'!C8,"") -> 5 | D151: =IF('Bill Master List'!F8="Yes",'Bill Master List'!D8,"") -> Card3 | E151: =IF('Bill Master List'!F8="Yes",'Bill Master List'!E8,"") -> Phone | F151: =IF('Bill Master List'!F8="Yes",'Bill Master List'!G8,"") -> 25 | G151: =IF('Bill Master List'!F8="Yes",'Bill Master List'!H8,"") -> 0 | H151: =IF('Bill Master List'!F8="Yes",'Bill Master List'!I8,"") -> Service disconnected after 30 days
A152: =IF('Bill Master List'!F9="Yes",'Bill Master List'!A9,"") -> Car Payment | B152: =IF('Bill Master List'!F9="Yes",'Bill Master List'!B9,"") -> 785 | C152: =IF('Bill Master List'!F9="Yes",'Bill Master List'!C9,"") -> 24 | D152: =IF('Bill Master List'!F9="Yes",'Bill Master List'!D9,"") -> Card3 | E152: =IF('Bill Master List'!F9="Yes",'Bill Master List'!E9,"") -> Auto | F152: =IF('Bill Master List'!F9="Yes",'Bill Master List'!G9,"") -> 39 | G152: =IF('Bill Master List'!F9="Yes",'Bill Master List'!H9,"") -> 10 | H152: =IF('Bill Master List'!F9="Yes",'Bill Master List'!I9,"") -> Repo risk after 60+ days. Hits credit report at 30 days.
A153: =IF('Bill Master List'!F10="Yes",'Bill Master List'!A10,"") -> Car Insurance | B153: =IF('Bill Master List'!F10="Yes",'Bill Master List'!B10,"") -> 0 | C153: =IF('Bill Master List'!F10="Yes",'Bill Master List'!C10,"") -> 10 | D153: =IF('Bill Master List'!F10="Yes",'Bill Master List'!D10,"") -> Card1 | E153: =IF('Bill Master List'!F10="Yes",'Bill Master List'!E10,"") -> Auto | F153: =IF('Bill Master List'!F10="Yes",'Bill Master List'!G10,"") -> 25 | G153: =IF('Bill Master List'!F10="Yes",'Bill Master List'!H10,"") -> 10 | H153: =IF('Bill Master List'!F10="Yes",'Bill Master List'!I10,"") -> Policy cancellation after lapse
A154: =IF('Bill Master List'!F11="Yes",'Bill Master List'!A11,"") -> Gas/Fuel | B154: =IF('Bill Master List'!F11="Yes",'Bill Master List'!B11,"") -> 200 | C154: =IF('Bill Master List'!F11="Yes",'Bill Master List'!C11,"") -> 15 | D154: =IF('Bill Master List'!F11="Yes",'Bill Master List'!D11,"") -> Card4 | E154: =IF('Bill Master List'!F11="Yes",'Bill Master List'!E11,"") -> Auto | F154: =IF('Bill Master List'!F11="Yes",'Bill Master List'!G11,"") -> 0 | G154: =IF('Bill Master List'!F11="Yes",'Bill Master List'!H11,"") -> 0 | H154: =IF('Bill Master List'!F11="Yes",'Bill Master List'!I11,"") -> Variable expense - no late fee
A155: =IF('Bill Master List'!F12="Yes",'Bill Master List'!A12,"") -> Groceries | B155: =IF('Bill Master List'!F12="Yes",'Bill Master List'!B12,"") -> 400 | C155: =IF('Bill Master List'!F12="Yes",'Bill Master List'!C12,"") -> 1 | D155: =IF('Bill Master List'!F12="Yes",'Bill Master List'!D12,"") -> Card3 | E155: =IF('Bill Master List'!F12="Yes",'Bill Master List'!E12,"") -> Health | F155: =IF('Bill Master List'!F12="Yes",'Bill Master List'!G12,"") -> 0 | G155: =IF('Bill Master List'!F12="Yes",'Bill Master List'!H12,"") -> 0 | H155: =IF('Bill Master List'!F12="Yes",'Bill Master List'!I12,"") -> Variable expense - no late fee
A156: =IF('Bill Master List'!F13="Yes",'Bill Master List'!A13,"") -> Klarna | B156: =IF('Bill Master List'!F13="Yes",'Bill Master List'!B13,"") -> 45 | C156: =IF('Bill Master List'!F13="Yes",'Bill Master List'!C13,"") -> 15 | D156: =IF('Bill Master List'!F13="Yes",'Bill Master List'!D13,"") -> Card2 | E156: =IF('Bill Master List'!F13="Yes",'Bill Master List'!E13,"") -> Entertainment | F156: =IF('Bill Master List'!F13="Yes",'Bill Master List'!G13,"") -> 25 | G156: =IF('Bill Master List'!F13="Yes",'Bill Master List'!H13,"") -> 0 | H156: =IF('Bill Master List'!F13="Yes",'Bill Master List'!I13,"") -> Hits credit after 30 days late
A157: =IF('Bill Master List'!F14="Yes",'Bill Master List'!A14,"") -> Affirm | B157: =IF('Bill Master List'!F14="Yes",'Bill Master List'!B14,"") -> 30 | C157: =IF('Bill Master List'!F14="Yes",'Bill Master List'!C14,"") -> 20 | D157: =IF('Bill Master List'!F14="Yes",'Bill Master List'!D14,"") -> Card5 | E157: =IF('Bill Master List'!F14="Yes",'Bill Master List'!E14,"") -> Food | F157: =IF('Bill Master List'!F14="Yes",'Bill Master List'!G14,"") -> 0 | G157: =IF('Bill Master List'!F14="Yes",'Bill Master List'!H14,"") -> 0 | H157: =IF('Bill Master List'!F14="Yes",'Bill Master List'!I14,"") -> No late fee but hits credit at 30 days
... A175: =IF('Bill Master List'!F32="Yes",'Bill Master List'!A32,"") | B175: =IF('Bill Master List'!F32="Yes",'Bill Master List'!B32,"") | C175: =IF('Bill Master List'!F32="Yes",'Bill Master List'!C32,"") | D175: =IF('Bill Master List'!F32="Yes",'Bill Master List'!D32,"") | E175: =IF('Bill Master List'!F32="Yes",'Bill Master List'!E32,"") | F175: =IF('Bill Master List'!F32="Yes",'Bill Master List'!G32,"") | G175: =IF('Bill Master List'!F32="Yes",'Bill Master List'!H32,"") | H175: =IF('Bill Master List'!F32="Yes",'Bill Master List'!I32,"")
A176: CARD TOTALS: | B176: Card1: | C176: Card2: | D176: Card3: | E176: Card4: | F176: Card5: | G176: MONTH TOTAL: | H176: Late Fee Risk:
B177: =SUMIF(D146:D175,"Card1",B146:B175) -> 587 | C177: =SUMIF(D146:D175,"Card2",B146:B175) -> 398 | D177: =SUMIF(D146:D175,"Card3",B146:B175) -> 1265 | E177: =SUMIF(D146:D175,"Card4",B146:B175) -> 200 | F177: =SUMIF(D146:D175,"Card5",B146:B175) -> 630 | G177: =SUM(B146:B175) -> 3080 | H177: =SUM(F146:F175) -> 249
A179: June 2026
A180: Bill Name | B180: Amount | C180: Due Day | D180: Pay Via (Card) | E180: Category | F180: Late Fee | G180: Grace Days | H180: Late Fee Notes
A181: =IF('Bill Master List'!F3="Yes",'Bill Master List'!A3,"") -> Storage 1 | B181: =IF('Bill Master List'!F3="Yes",'Bill Master List'!B3,"") -> 478 | C181: =IF('Bill Master List'!F3="Yes",'Bill Master List'!C3,"") -> 1 | D181: =IF('Bill Master List'!F3="Yes",'Bill Master List'!D3,"") -> Card1 | E181: =IF('Bill Master List'!F3="Yes",'Bill Master List'!E3,"") -> Housing | F181: =IF('Bill Master List'!F3="Yes",'Bill Master List'!G3,"") -> 40 | G181: =IF('Bill Master List'!F3="Yes",'Bill Master List'!H3,"") -> 5 | H181: =IF('Bill Master List'!F3="Yes",'Bill Master List'!I3,"") -> Lien risk after 30 days late
A182: =IF('Bill Master List'!F4="Yes",'Bill Master List'!A4,"") -> Storage 2 | B182: =IF('Bill Master List'!F4="Yes",'Bill Master List'!B4,"") -> 109 | C182: =IF('Bill Master List'!F4="Yes",'Bill Master List'!C4,"") -> 1 | D182: =IF('Bill Master List'!F4="Yes",'Bill Master List'!D4,"") -> Card1 | E182: =IF('Bill Master List'!F4="Yes",'Bill Master List'!E4,"") -> Housing | F182: =IF('Bill Master List'!F4="Yes",'Bill Master List'!G4,"") -> 25 | G182: =IF('Bill Master List'!F4="Yes",'Bill Master List'!H4,"") -> 5 | H182: =IF('Bill Master List'!F4="Yes",'Bill Master List'!I4,"") -> Lien risk after 30 days late
A183: =IF('Bill Master List'!F5="Yes",'Bill Master List'!A5,"") -> Storage 3 | B183: =IF('Bill Master List'!F5="Yes",'Bill Master List'!B5,"") -> 180 | C183: =IF('Bill Master List'!F5="Yes",'Bill Master List'!C5,"") -> 1 | D183: =IF('Bill Master List'!F5="Yes",'Bill Master List'!D5,"") -> Card2 | E183: =IF('Bill Master List'!F5="Yes",'Bill Master List'!E5,"") -> Housing | F183: =IF('Bill Master List'!F5="Yes",'Bill Master List'!G5,"") -> 25 | G183: =IF('Bill Master List'!F5="Yes",'Bill Master List'!H5,"") -> 5 | H183: =IF('Bill Master List'!F5="Yes",'Bill Master List'!I5,"") -> Lien risk after 30 days late
A184: =IF('Bill Master List'!F6="Yes",'Bill Master List'!A6,"") -> Storage 4 | B184: =IF('Bill Master List'!F6="Yes",'Bill Master List'!B6,"") -> 98 | C184: =IF('Bill Master List'!F6="Yes",'Bill Master List'!C6,"") -> 1 | D184: =IF('Bill Master List'!F6="Yes",'Bill Master List'!D6,"") -> Card2 | E184: =IF('Bill Master List'!F6="Yes",'Bill Master List'!E6,"") -> Housing | F184: =IF('Bill Master List'!F6="Yes",'Bill Master List'!G6,"") -> 20 | G184: =IF('Bill Master List'!F6="Yes",'Bill Master List'!H6,"") -> 5 | H184: =IF('Bill Master List'!F6="Yes",'Bill Master List'!I6,"") -> Lien risk after 30 days late
A185: =IF('Bill Master List'!F7="Yes",'Bill Master List'!A7,"") -> Intuit | B185: =IF('Bill Master List'!F7="Yes",'Bill Master List'!B7,"") -> 75 | C185: =IF('Bill Master List'!F7="Yes",'Bill Master List'!C7,"") -> 20 | D185: =IF('Bill Master List'!F7="Yes",'Bill Master List'!D7,"") -> Card2 | E185: =IF('Bill Master List'!F7="Yes",'Bill Master List'!E7,"") -> Utilities | F185: =IF('Bill Master List'!F7="Yes",'Bill Master List'!G7,"") -> 0 | G185: =IF('Bill Master List'!F7="Yes",'Bill Master List'!H7,"") -> 0 | H185: =IF('Bill Master List'!F7="Yes",'Bill Master List'!I7,"") -> Service suspended if unpaid
A186: =IF('Bill Master List'!F8="Yes",'Bill Master List'!A8,"") -> Cell Phone | B186: =IF('Bill Master List'!F8="Yes",'Bill Master List'!B8,"") -> 80 | C186: =IF('Bill Master List'!F8="Yes",'Bill Master List'!C8,"") -> 5 | D186: =IF('Bill Master List'!F8="Yes",'Bill Master List'!D8,"") -> Card3 | E186: =IF('Bill Master List'!F8="Yes",'Bill Master List'!E8,"") -> Phone | F186: =IF('Bill Master List'!F8="Yes",'Bill Master List'!G8,"") -> 25 | G186: =IF('Bill Master List'!F8="Yes",'Bill Master List'!H8,"") -> 0 | H186: =IF('Bill Master List'!F8="Yes",'Bill Master List'!I8,"") -> Service disconnected after 30 days
A187: =IF('Bill Master List'!F9="Yes",'Bill Master List'!A9,"") -> Car Payment | B187: =IF('Bill Master List'!F9="Yes",'Bill Master List'!B9,"") -> 785 | C187: =IF('Bill Master List'!F9="Yes",'Bill Master List'!C9,"") -> 24 | D187: =IF('Bill Master List'!F9="Yes",'Bill Master List'!D9,"") -> Card3 | E187: =IF('Bill Master List'!F9="Yes",'Bill Master List'!E9,"") -> Auto | F187: =IF('Bill Master List'!F9="Yes",'Bill Master List'!G9,"") -> 39 | G187: =IF('Bill Master List'!F9="Yes",'Bill Master List'!H9,"") -> 10 | H187: =IF('Bill Master List'!F9="Yes",'Bill Master List'!I9,"") -> Repo risk after 60+ days. Hits credit report at 30 days.
A188: =IF('Bill Master List'!F10="Yes",'Bill Master List'!A10,"") -> Car Insurance | B188: =IF('Bill Master List'!F10="Yes",'Bill Master List'!B10,"") -> 0 | C188: =IF('Bill Master List'!F10="Yes",'Bill Master List'!C10,"") -> 10 | D188: =IF('Bill Master List'!F10="Yes",'Bill Master List'!D10,"") -> Card1 | E188: =IF('Bill Master List'!F10="Yes",'Bill Master List'!E10,"") -> Auto | F188: =IF('Bill Master List'!F10="Yes",'Bill Master List'!G10,"") -> 25 | G188: =IF('Bill Master List'!F10="Yes",'Bill Master List'!H10,"") -> 10 | H188: =IF('Bill Master List'!F10="Yes",'Bill Master List'!I10,"") -> Policy cancellation after lapse
A189: =IF('Bill Master List'!F11="Yes",'Bill Master List'!A11,"") -> Gas/Fuel | B189: =IF('Bill Master List'!F11="Yes",'Bill Master List'!B11,"") -> 200 | C189: =IF('Bill Master List'!F11="Yes",'Bill Master List'!C11,"") -> 15 | D189: =IF('Bill Master List'!F11="Yes",'Bill Master List'!D11,"") -> Card4 | E189: =IF('Bill Master List'!F11="Yes",'Bill Master List'!E11,"") -> Auto | F189: =IF('Bill Master List'!F11="Yes",'Bill Master List'!G11,"") -> 0 | G189: =IF('Bill Master List'!F11="Yes",'Bill Master List'!H11,"") -> 0 | H189: =IF('Bill Master List'!F11="Yes",'Bill Master List'!I11,"") -> Variable expense - no late fee
...

Sheet Utilization Alerts
A1: CREDIT UTILIZATION ALERT SYSTEM
A2: Real-time monitoring: Stay under 30% (ideally under 10%) for optimal credit score
A4: CURRENT CARD STATUS
A5: Card ID | B5: Bank | C5: Current Balance | D5: Credit Limit | E5: Available Credit | F5: Utilization % | G5: Status | H5: Monthly Bills | I5: Danger Level | J5: Action Needed
A6: ='Credit Cards'!A3 -> Card1 | B6: ='Credit Cards'!B3 -> Navy Federal Card | C6: ='Credit Cards'!M3 -> 1500.1 | D6: ='Credit Cards'!C3 -> 1500 | E6: =D6-C6 -> -0.1 | F6: =IF(D6>0,C6/D6,0) -> 1.0000667 | G6: =IF(F6=0,"Inactive",IF(F6<0.1,"✓ SAFE",IF(F6<0.3,"⚠ Warning",IF(F6<0.5,"🔶 CAUTION","🚨 DANGER")))) -> 🚨 DANGER | H6: =SUMIF('Bill Master List'!D:D,"Card1",'Bill Master List'!B:B) -> 587 | I6: =IF(F6<0.1,1,IF(F6<0.3,2,IF(F6<0.5,3,4))) -> 4 | J6: =IF(F6=0,"N/A",IF(F6<0.1,"None - Keep it up!",IF(F6<0.3,"Consider paying down",IF(F6<0.5,"PAY DOWN ASAP!","CRITICAL - Pay immediately!")))) -> CRITICAL - Pay immediately!
A7: ='Credit Cards'!A4 -> Card2 | B7: ='Credit Cards'!B4 -> Indigo 3069 | C7: ='Credit Cards'!M4 -> 632.81 | D7: ='Credit Cards'!C4 -> 500 | E7: =D7-C7 -> -132.81 | F7: =IF(D7>0,C7/D7,0) -> 1.26562 | G7: =IF(F7=0,"Inactive",IF(F7<0.1,"✓ SAFE",IF(F7<0.3,"⚠ Warning",IF(F7<0.5,"🔶 CAUTION","🚨 DANGER")))) -> 🚨 DANGER | H7: =SUMIF('Bill Master List'!D:D,"Card2",'Bill Master List'!B:B) -> 398 | I7: =IF(F7<0.1,1,IF(F7<0.3,2,IF(F7<0.5,3,4))) -> 4 | J7: =IF(F7=0,"N/A",IF(F7<0.1,"None - Keep it up!",IF(F7<0.3,"Consider paying down",IF(F7<0.5,"PAY DOWN ASAP!","CRITICAL - Pay immediately!")))) -> CRITICAL - Pay immediately!
A8: ='Credit Cards'!A5 -> Card3 | B8: ='Credit Cards'!B5 -> Indigo 1448 | C8: ='Credit Cards'!M5 -> 547.97 | D8: ='Credit Cards'!C5 -> 1000 | E8: =D8-C8 -> 452.03 | F8: =IF(D8>0,C8/D8,0) -> 0.54797 | G8: =IF(F8=0,"Inactive",IF(F8<0.1,"✓ SAFE",IF(F8<0.3,"⚠ Warning",IF(F8<0.5,"🔶 CAUTION","🚨 DANGER")))) -> 🚨 DANGER | H8: =SUMIF('Bill Master List'!D:D,"Card3",'Bill Master List'!B:B) -> 1265 | I8: =IF(F8<0.1,1,IF(F8<0.3,2,IF(F8<0.5,3,4))) -> 4 | J8: =IF(F8=0,"N/A",IF(F8<0.1,"None - Keep it up!",IF(F8<0.3,"Consider paying down",IF(F8<0.5,"PAY DOWN ASAP!","CRITICAL - Pay immediately!")))) -> CRITICAL - Pay immediately!
A9: ='Credit Cards'!A6 -> Card4 | B9: ='Credit Cards'!B6 -> Milestone 5093 | C9: ='Credit Cards'!M6 -> 489.81 | D9: ='Credit Cards'!C6 -> 500 | E9: =D9-C9 -> 10.19 | F9: =IF(D9>0,C9/D9,0) -> 0.97962 | G9: =IF(F9=0,"Inactive",IF(F9<0.1,"✓ SAFE",IF(F9<0.3,"⚠ Warning",IF(F9<0.5,"🔶 CAUTION","🚨 DANGER")))) -> 🚨 DANGER | H9: =SUMIF('Bill Master List'!D:D,"Card4",'Bill Master List'!B:B) -> 200 | I9: =IF(F9<0.1,1,IF(F9<0.3,2,IF(F9<0.5,3,4))) -> 4 | J9: =IF(F9=0,"N/A",IF(F9<0.1,"None - Keep it up!",IF(F9<0.3,"Consider paying down",IF(F9<0.5,"PAY DOWN ASAP!","CRITICAL - Pay immediately!")))) -> CRITICAL - Pay immediately!
A10: ='Credit Cards'!A7 -> Card5 | B10: ='Credit Cards'!B7 -> Destiny 3992 | C10: ='Credit Cards'!M7 -> 958.34 | D10: ='Credit Cards'!C7 -> 1000 | E10: =D10-C10 -> 41.66 | F10: =IF(D10>0,C10/D10,0) -> 0.95834 | G10: =IF(F10=0,"Inactive",IF(F10<0.1,"✓ SAFE",IF(F10<0.3,"⚠ Warning",IF(F10<0.5,"🔶 CAUTION","🚨 DANGER")))) -> 🚨 DANGER | H10: =SUMIF('Bill Master List'!D:D,"Card5",'Bill Master List'!B:B) -> 630 | I10: =IF(F10<0.1,1,IF(F10<0.3,2,IF(F10<0.5,3,4))) -> 4 | J10: =IF(F10=0,"N/A",IF(F10<0.1,"None - Keep it up!",IF(F10<0.3,"Consider paying down",IF(F10<0.5,"PAY DOWN ASAP!","CRITICAL - Pay immediately!")))) -> CRITICAL - Pay immediately!
A11: ='Credit Cards'!A8 -> Card6 | B11: ='Credit Cards'!B8 -> 0 | C11: ='Credit Cards'!M8 -> 0 | D11: ='Credit Cards'!C8 -> 0 | E11: =D11-C11 -> 0 | F11: =IF(D11>0,C11/D11,0) -> 0 | G11: =IF(F11=0,"Inactive",IF(F11<0.1,"✓ SAFE",IF(F11<0.3,"⚠ Warning",IF(F11<0.5,"🔶 CAUTION","🚨 DANGER")))) -> Inactive | H11: =SUMIF('Bill Master List'!D:D,"Card6",'Bill Master List'!B:B) -> 0 | I11: =IF(F11<0.1,1,IF(F11<0.3,2,IF(F11<0.5,3,4))) -> 1 | J11: =IF(F11=0,"N/A",IF(F11<0.1,"None - Keep it up!",IF(F11<0.3,"Consider paying down",IF(F11<0.5,"PAY DOWN ASAP!","CRITICAL - Pay immediately!")))) -> N/A
A12: ='Credit Cards'!A9 -> Card7 | B12: ='Credit Cards'!B9 -> 0 | C12: ='Credit Cards'!M9 -> 0 | D12: ='Credit Cards'!C9 -> 0 | E12: =D12-C12 -> 0 | F12: =IF(D12>0,C12/D12,0) -> 0 | G12: =IF(F12=0,"Inactive",IF(F12<0.1,"✓ SAFE",IF(F12<0.3,"⚠ Warning",IF(F12<0.5,"🔶 CAUTION","🚨 DANGER")))) -> Inactive | H12: =SUMIF('Bill Master List'!D:D,"Card7",'Bill Master List'!B:B) -> 0 | I12: =IF(F12<0.1,1,IF(F12<0.3,2,IF(F12<0.5,3,4))) -> 1 | J12: =IF(F12=0,"N/A",IF(F12<0.1,"None - Keep it up!",IF(F12<0.3,"Consider paying down",IF(F12<0.5,"PAY DOWN ASAP!","CRITICAL - Pay immediately!")))) -> N/A
A13: ='Credit Cards'!A10 -> Card8 | B13: ='Credit Cards'!B10 -> 0 | C13: ='Credit Cards'!M10 -> 0 | D13: ='Credit Cards'!C10 -> 0 | E13: =D13-C13 -> 0 | F13: =IF(D13>0,C13/D13,0) -> 0 | G13: =IF(F13=0,"Inactive",IF(F13<0.1,"✓ SAFE",IF(F13<0.3,"⚠ Warning",IF(F13<0.5,"🔶 CAUTION","🚨 DANGER")))) -> Inactive | H13: =SUMIF('Bill Master List'!D:D,"Card8",'Bill Master List'!B:B) -> 0 | I13: =IF(F13<0.1,1,IF(F13<0.3,2,IF(F13<0.5,3,4))) -> 1 | J13: =IF(F13=0,"N/A",IF(F13<0.1,"None - Keep it up!",IF(F13<0.3,"Consider paying down",IF(F13<0.5,"PAY DOWN ASAP!","CRITICAL - Pay immediately!")))) -> N/A
A14: ='Credit Cards'!A11 -> Card9 | B14: ='Credit Cards'!B11 -> 0 | C14: ='Credit Cards'!M11 -> 0 | D14: ='Credit Cards'!C11 -> 0 | E14: =D14-C14 -> 0 | F14: =IF(D14>0,C14/D14,0) -> 0 | G14: =IF(F14=0,"Inactive",IF(F14<0.1,"✓ SAFE",IF(F14<0.3,"⚠ Warning",IF(F14<0.5,"🔶 CAUTION","🚨 DANGER")))) -> Inactive | H14: =SUMIF('Bill Master List'!D:D,"Card9",'Bill Master List'!B:B) -> 0 | I14: =IF(F14<0.1,1,IF(F14<0.3,2,IF(F14<0.5,3,4))) -> 1 | J14: =IF(F14=0,"N/A",IF(F14<0.1,"None - Keep it up!",IF(F14<0.3,"Consider paying down",IF(F14<0.5,"PAY DOWN ASAP!","CRITICAL - Pay immediately!")))) -> N/A
A15: ='Credit Cards'!A12 -> Card10 | B15: ='Credit Cards'!B12 -> 0 | C15: ='Credit Cards'!M12 -> 0 | D15: ='Credit Cards'!C12 -> 0 | E15: =D15-C15 -> 0 | F15: =IF(D15>0,C15/D15,0) -> 0 | G15: =IF(F15=0,"Inactive",IF(F15<0.1,"✓ SAFE",IF(F15<0.3,"⚠ Warning",IF(F15<0.5,"🔶 CAUTION","🚨 DANGER")))) -> Inactive | H15: =SUMIF('Bill Master List'!D:D,"Card10",'Bill Master List'!B:B) -> 0 | I15: =IF(F15<0.1,1,IF(F15<0.3,2,IF(F15<0.5,3,4))) -> 1 | J15: =IF(F15=0,"N/A",IF(F15<0.1,"None - Keep it up!",IF(F15<0.3,"Consider paying down",IF(F15<0.5,"PAY DOWN ASAP!","CRITICAL - Pay immediately!")))) -> N/A
A16: ='Credit Cards'!A13 -> Card11 | B16: ='Credit Cards'!B13 -> 0 | C16: ='Credit Cards'!M13 -> 0 | D16: ='Credit Cards'!C13 -> 0 | E16: =D16-C16 -> 0 | F16: =IF(D16>0,C16/D16,0) -> 0 | G16: =IF(F16=0,"Inactive",IF(F16<0.1,"✓ SAFE",IF(F16<0.3,"⚠ Warning",IF(F16<0.5,"🔶 CAUTION","🚨 DANGER")))) -> Inactive | H16: =SUMIF('Bill Master List'!D:D,"Card11",'Bill Master List'!B:B) -> 0 | I16: =IF(F16<0.1,1,IF(F16<0.3,2,IF(F16<0.5,3,4))) -> 1 | J16: =IF(F16=0,"N/A",IF(F16<0.1,"None - Keep it up!",IF(F16<0.3,"Consider paying down",IF(F16<0.5,"PAY DOWN ASAP!","CRITICAL - Pay immediately!")))) -> N/A
A17: ='Credit Cards'!A14 -> Card12 | B17: ='Credit Cards'!B14 -> 0 | C17: ='Credit Cards'!M14 -> 0 | D17: ='Credit Cards'!C14 -> 0 | E17: =D17-C17 -> 0 | F17: =IF(D17>0,C17/D17,0) -> 0 | G17: =IF(F17=0,"Inactive",IF(F17<0.1,"✓ SAFE",IF(F17<0.3,"⚠ Warning",IF(F17<0.5,"🔶 CAUTION","🚨 DANGER")))) -> Inactive | H17: =SUMIF('Bill Master List'!D:D,"Card12",'Bill Master List'!B:B) -> 0 | I17: =IF(F17<0.1,1,IF(F17<0.3,2,IF(F17<0.5,3,4))) -> 1 | J17: =IF(F17=0,"N/A",IF(F17<0.1,"None - Keep it up!",IF(F17<0.3,"Consider paying down",IF(F17<0.5,"PAY DOWN ASAP!","CRITICAL - Pay immediately!")))) -> N/A
A18: ='Credit Cards'!A15 -> Card13 | B18: ='Credit Cards'!B15 -> 0 | C18: ='Credit Cards'!M15 -> 0 | D18: ='Credit Cards'!C15 -> 0 | E18: =D18-C18 -> 0 | F18: =IF(D18>0,C18/D18,0) -> 0 | G18: =IF(F18=0,"Inactive",IF(F18<0.1,"✓ SAFE",IF(F18<0.3,"⚠ Warning",IF(F18<0.5,"🔶 CAUTION","🚨 DANGER")))) -> Inactive | H18: =SUMIF('Bill Master List'!D:D,"Card13",'Bill Master List'!B:B) -> 0 | I18: =IF(F18<0.1,1,IF(F18<0.3,2,IF(F18<0.5,3,4))) -> 1 | J18: =IF(F18=0,"N/A",IF(F18<0.1,"None - Keep it up!",IF(F18<0.3,"Consider paying down",IF(F18<0.5,"PAY DOWN ASAP!","CRITICAL - Pay immediately!")))) -> N/A
A19: ='Credit Cards'!A16 -> Card14 | B19: ='Credit Cards'!B16 -> 0 | C19: ='Credit Cards'!M16 -> 0 | D19: ='Credit Cards'!C16 -> 0 | E19: =D19-C19 -> 0 | F19: =IF(D19>0,C19/D19,0) -> 0 | G19: =IF(F19=0,"Inactive",IF(F19<0.1,"✓ SAFE",IF(F19<0.3,"⚠ Warning",IF(F19<0.5,"🔶 CAUTION","🚨 DANGER")))) -> Inactive | H19: =SUMIF('Bill Master List'!D:D,"Card14",'Bill Master List'!B:B) -> 0 | I19: =IF(F19<0.1,1,IF(F19<0.3,2,IF(F19<0.5,3,4))) -> 1 | J19: =IF(F19=0,"N/A",IF(F19<0.1,"None - Keep it up!",IF(F19<0.3,"Consider paying down",IF(F19<0.5,"PAY DOWN ASAP!","CRITICAL - Pay immediately!")))) -> N/A
A20: ='Credit Cards'!A17 -> Card15 | B20: ='Credit Cards'!B17 -> 0 | C20: ='Credit Cards'!M17 -> 0 | D20: ='Credit Cards'!C17 -> 0 | E20: =D20-C20 -> 0 | F20: =IF(D20>0,C20/D20,0) -> 0 | G20: =IF(F20=0,"Inactive",IF(F20<0.1,"✓ SAFE",IF(F20<0.3,"⚠ Warning",IF(F20<0.5,"🔶 CAUTION","🚨 DANGER")))) -> Inactive | H20: =SUMIF('Bill Master List'!D:D,"Card15",'Bill Master List'!B:B) -> 0 | I20: =IF(F20<0.1,1,IF(F20<0.3,2,IF(F20<0.5,3,4))) -> 1 | J20: =IF(F20=0,"N/A",IF(F20<0.1,"None - Keep it up!",IF(F20<0.3,"Consider paying down",IF(F20<0.5,"PAY DOWN ASAP!","CRITICAL - Pay immediately!")))) -> N/A
A23: UTILIZATION SUMMARY
A24: Status Level | B24: Utilization Range | C24: Impact on Credit | D24: Card Count | E24: Total Balance
A25: ✓ SAFE | B25: Under 10% | C25: Excellent! | D25: =COUNTIFS(F6:F20,"<0.10",F6:F20,">0") -> 0 | E25: =SUMIF(F6:F20,"<0.10",C6:C20) -> 0
A26: ⚠ Warning | B26: 10% - 29.9% | C26: Watch closely | D26: =COUNTIFS(F6:F20,">=0.10",F6:F20,"<0.30") -> 0 | E26: =SUMIFS(C6:C20,F6:F20,">=0.10",F6:F20,"<0.30") -> 0
A27: 🔶 CAUTION | B27: 30% - 49.9% | C27: Hurts score! | D27: =COUNTIFS(F6:F20,">=0.30",F6:F20,"<0.50") -> 0 | E27: =SUMIFS(C6:C20,F6:F20,">=0.30",F6:F20,"<0.50") -> 0
A28: 🚨 DANGER | B28: 50%+ | C28: Major damage! | D28: =COUNTIF(F6:F20,">=0.50") -> 5 | E28: =SUMIF(F6:F20,">=0.50",C6:C20) -> 4129.03
A31: OVERALL METRICS
A32: Total Credit Limit: | B32: =SUM(D6:D20) -> 4500 | D32: Active Cards: | E32: =COUNTIF('Credit Cards'!K3:K17,"Yes") -> 5
A33: Total Balance: | B33: =SUM(C6:C20) -> 4129.03 | D33: Cards Over 30%: | E33: =COUNTIF(F6:F20,">=0.30") -> 5
A34: Total Available: | B34: =SUM(E6:E20) -> 370.97 | D34: Cards Over 50%: | E34: =COUNTIF(F6:F20,">=0.50") -> 5
A35: Overall Utilization: | B35: =IF(SUM(D6:D20)>0,SUM(C6:C20)/SUM(D6:D20),0) -> 0.91756222 | D35: Avg Utilization: | E35: =AVERAGE(F6:F20) -> 0.31677444

Sheet Smart Bill Assignments
A1: SMART BILL ASSIGNMENT ENGINE
A2: Tells you EXACTLY which card to use for each bill to stay under 30% utilization
A4: CARD CAPACITY OVERVIEW (How much room each card has)
A5: Card ID | B5: Bank | C5: Credit Limit | D5: Current Balance | E5: 30% Threshold | F5: Room to 30% | G5: 10% Threshold | H5: Room to 10% | I5: Bills Assigned | J5: Balance After Bills | K5: Util After Bills | L5: Status After Bills
A6: ='Credit Cards'!A3 -> Card1 | B6: ='Credit Cards'!B3 -> Navy Federal Card | C6: ='Credit Cards'!C3 -> 1500 | D6: ='Credit Cards'!H3 -> 1500.1 | E6: =C6*0.3 -> 450 | F6: =MAX(E6-D6,0) -> 0 | G6: =C6*0.1 -> 150 | H6: =MAX(G6-D6,0) -> 0 | I6: =SUMIF('Bill Master List'!D:D,"Card1",'Bill Master List'!B:B) -> 587 | J6: =D6+I6 -> 2087.1 | K6: =IF(C6>0,J6/C6,0) -> 1.3914 | L6: =IF(C6=0,"Inactive",IF(K6<0.1,"✓ SAFE",IF(K6<0.3,"⚠ Warning",IF(K6<0.5,"🔶 CAUTION","🚨 DANGER")))) -> 🚨 DANGER
A7: ='Credit Cards'!A4 -> Card2 | B7: ='Credit Cards'!B4 -> Indigo 3069 | C7: ='Credit Cards'!C4 -> 500 | D7: ='Credit Cards'!H4 -> 632.81 | E7: =C7*0.3 -> 150 | F7: =MAX(E7-D7,0) -> 0 | G7: =C7*0.1 -> 50 | H7: =MAX(G7-D7,0) -> 0 | I7: =SUMIF('Bill Master List'!D:D,"Card2",'Bill Master List'!B:B) -> 398 | J7: =D7+I7 -> 1030.81 | K7: =IF(C7>0,J7/C7,0) -> 2.06162 | L7: =IF(C7=0,"Inactive",IF(K7<0.1,"✓ SAFE",IF(K7<0.3,"⚠ Warning",IF(K7<0.5,"🔶 CAUTION","🚨 DANGER")))) -> 🚨 DANGER
A8: ='Credit Cards'!A5 -> Card3 | B8: ='Credit Cards'!B5 -> Indigo 1448 | C8: ='Credit Cards'!C5 -> 1000 | D8: ='Credit Cards'!H5 -> 599.4 | E8: =C8*0.3 -> 300 | F8: =MAX(E8-D8,0) -> 0 | G8: =C8*0.1 -> 100 | H8: =MAX(G8-D8,0) -> 0 | I8: =SUMIF('Bill Master List'!D:D,"Card3",'Bill Master List'!B:B) -> 1265 | J8: =D8+I8 -> 1864.4 | K8: =IF(C8>0,J8/C8,0) -> 1.8644 | L8: =IF(C8=0,"Inactive",IF(K8<0.1,"✓ SAFE",IF(K8<0.3,"⚠ Warning",IF(K8<0.5,"🔶 CAUTION","🚨 DANGER")))) -> 🚨 DANGER
A9: ='Credit Cards'!A6 -> Card4 | B9: ='Credit Cards'!B6 -> Milestone 5093 | C9: ='Credit Cards'!C6 -> 500 | D9: ='Credit Cards'!H6 -> 489.81 | E9: =C9*0.3 -> 150 | F9: =MAX(E9-D9,0) -> 0 | G9: =C9*0.1 -> 50 | H9: =MAX(G9-D9,0) -> 0 | I9: =SUMIF('Bill Master List'!D:D,"Card4",'Bill Master List'!B:B) -> 200 | J9: =D9+I9 -> 689.81 | K9: =IF(C9>0,J9/C9,0) -> 1.37962 | L9: =IF(C9=0,"Inactive",IF(K9<0.1,"✓ SAFE",IF(K9<0.3,"⚠ Warning",IF(K9<0.5,"🔶 CAUTION","🚨 DANGER")))) -> 🚨 DANGER
A10: ='Credit Cards'!A7 -> Card5 | B10: ='Credit Cards'!B7 -> Destiny 3992 | C10: ='Credit Cards'!C7 -> 1000 | D10: ='Credit Cards'!H7 -> 944.27 | E10: =C10*0.3 -> 300 | F10: =MAX(E10-D10,0) -> 0 | G10: =C10*0.1 -> 100 | H10: =MAX(G10-D10,0) -> 0 | I10: =SUMIF('Bill Master List'!D:D,"Card5",'Bill Master List'!B:B) -> 630 | J10: =D10+I10 -> 1574.27 | K10: =IF(C10>0,J10/C10,0) -> 1.57427 | L10: =IF(C10=0,"Inactive",IF(K10<0.1,"✓ SAFE",IF(K10<0.3,"⚠ Warning",IF(K10<0.5,"🔶 CAUTION","🚨 DANGER")))) -> 🚨 DANGER
A11: ='Credit Cards'!A8 -> Card6 | B11: ='Credit Cards'!B8 -> 0 | C11: ='Credit Cards'!C8 -> 0 | D11: ='Credit Cards'!H8 -> 0 | E11: =C11*0.3 -> 0 | F11: =MAX(E11-D11,0) -> 0 | G11: =C11*0.1 -> 0 | H11: =MAX(G11-D11,0) -> 0 | I11: =SUMIF('Bill Master List'!D:D,"Card6",'Bill Master List'!B:B) -> 0 | J11: =D11+I11 -> 0 | K11: =IF(C11>0,J11/C11,0) -> 0 | L11: =IF(C11=0,"Inactive",IF(K11<0.1,"✓ SAFE",IF(K11<0.3,"⚠ Warning",IF(K11<0.5,"🔶 CAUTION","🚨 DANGER")))) -> Inactive
A12: ='Credit Cards'!A9 -> Card7 | B12: ='Credit Cards'!B9 -> 0 | C12: ='Credit Cards'!C9 -> 0 | D12: ='Credit Cards'!H9 -> 0 | E12: =C12*0.3 -> 0 | F12: =MAX(E12-D12,0) -> 0 | G12: =C12*0.1 -> 0 | H12: =MAX(G12-D12,0) -> 0 | I12: =SUMIF('Bill Master List'!D:D,"Card7",'Bill Master List'!B:B) -> 0 | J12: =D12+I12 -> 0 | K12: =IF(C12>0,J12/C12,0) -> 0 | L12: =IF(C12=0,"Inactive",IF(K12<0.1,"✓ SAFE",IF(K12<0.3,"⚠ Warning",IF(K12<0.5,"🔶 CAUTION","🚨 DANGER")))) -> Inactive
A13: ='Credit Cards'!A10 -> Card8 | B13: ='Credit Cards'!B10 -> 0 | C13: ='Credit Cards'!C10 -> 0 | D13: ='Credit Cards'!H10 -> 0 | E13: =C13*0.3 -> 0 | F13: =MAX(E13-D13,0) -> 0 | G13: =C13*0.1 -> 0 | H13: =MAX(G13-D13,0) -> 0 | I13: =SUMIF('Bill Master List'!D:D,"Card8",'Bill Master List'!B:B) -> 0 | J13: =D13+I13 -> 0 | K13: =IF(C13>0,J13/C13,0) -> 0 | L13: =IF(C13=0,"Inactive",IF(K13<0.1,"✓ SAFE",IF(K13<0.3,"⚠ Warning",IF(K13<0.5,"🔶 CAUTION","🚨 DANGER")))) -> Inactive
A14: ='Credit Cards'!A11 -> Card9 | B14: ='Credit Cards'!B11 -> 0 | C14: ='Credit Cards'!C11 -> 0 | D14: ='Credit Cards'!H11 -> 0 | E14: =C14*0.3 -> 0 | F14: =MAX(E14-D14,0) -> 0 | G14: =C14*0.1 -> 0 | H14: =MAX(G14-D14,0) -> 0 | I14: =SUMIF('Bill Master List'!D:D,"Card9",'Bill Master List'!B:B) -> 0 | J14: =D14+I14 -> 0 | K14: =IF(C14>0,J14/C14,0) -> 0 | L14: =IF(C14=0,"Inactive",IF(K14<0.1,"✓ SAFE",IF(K14<0.3,"⚠ Warning",IF(K14<0.5,"🔶 CAUTION","🚨 DANGER")))) -> Inactive
A15: ='Credit Cards'!A12 -> Card10 | B15: ='Credit Cards'!B12 -> 0 | C15: ='Credit Cards'!C12 -> 0 | D15: ='Credit Cards'!H12 -> 0 | E15: =C15*0.3 -> 0 | F15: =MAX(E15-D15,0) -> 0 | G15: =C15*0.1 -> 0 | H15: =MAX(G15-D15,0) -> 0 | I15: =SUMIF('Bill Master List'!D:D,"Card10",'Bill Master List'!B:B) -> 0 | J15: =D15+I15 -> 0 | K15: =IF(C15>0,J15/C15,0) -> 0 | L15: =IF(C15=0,"Inactive",IF(K15<0.1,"✓ SAFE",IF(K15<0.3,"⚠ Warning",IF(K15<0.5,"🔶 CAUTION","🚨 DANGER")))) -> Inactive
A16: ='Credit Cards'!A13 -> Card11 | B16: ='Credit Cards'!B13 -> 0 | C16: ='Credit Cards'!C13 -> 0 | D16: ='Credit Cards'!H13 -> 0 | E16: =C16*0.3 -> 0 | F16: =MAX(E16-D16,0) -> 0 | G16: =C16*0.1 -> 0 | H16: =MAX(G16-D16,0) -> 0 | I16: =SUMIF('Bill Master List'!D:D,"Card11",'Bill Master List'!B:B) -> 0 | J16: =D16+I16 -> 0 | K16: =IF(C16>0,J16/C16,0) -> 0 | L16: =IF(C16=0,"Inactive",IF(K16<0.1,"✓ SAFE",IF(K16<0.3,"⚠ Warning",IF(K16<0.5,"🔶 CAUTION","🚨 DANGER")))) -> Inactive
A17: ='Credit Cards'!A14 -> Card12 | B17: ='Credit Cards'!B14 -> 0 | C17: ='Credit Cards'!C14 -> 0 | D17: ='Credit Cards'!H14 -> 0 | E17: =C17*0.3 -> 0 | F17: =MAX(E17-D17,0) -> 0 | G17: =C17*0.1 -> 0 | H17: =MAX(G17-D17,0) -> 0 | I17: =SUMIF('Bill Master List'!D:D,"Card12",'Bill Master List'!B:B) -> 0 | J17: =D17+I17 -> 0 | K17: =IF(C17>0,J17/C17,0) -> 0 | L17: =IF(C17=0,"Inactive",IF(K17<0.1,"✓ SAFE",IF(K17<0.3,"⚠ Warning",IF(K17<0.5,"🔶 CAUTION","🚨 DANGER")))) -> Inactive
A18: ='Credit Cards'!A15 -> Card13 | B18: ='Credit Cards'!B15 -> 0 | C18: ='Credit Cards'!C15 -> 0 | D18: ='Credit Cards'!H15 -> 0 | E18: =C18*0.3 -> 0 | F18: =MAX(E18-D18,0) -> 0 | G18: =C18*0.1 -> 0 | H18: =MAX(G18-D18,0) -> 0 | I18: =SUMIF('Bill Master List'!D:D,"Card13",'Bill Master List'!B:B) -> 0 | J18: =D18+I18 -> 0 | K18: =IF(C18>0,J18/C18,0) -> 0 | L18: =IF(C18=0,"Inactive",IF(K18<0.1,"✓ SAFE",IF(K18<0.3,"⚠ Warning",IF(K18<0.5,"🔶 CAUTION","🚨 DANGER")))) -> Inactive
A19: ='Credit Cards'!A16 -> Card14 | B19: ='Credit Cards'!B16 -> 0 | C19: ='Credit Cards'!C16 -> 0 | D19: ='Credit Cards'!H16 -> 0 | E19: =C19*0.3 -> 0 | F19: =MAX(E19-D19,0) -> 0 | G19: =C19*0.1 -> 0 | H19: =MAX(G19-D19,0) -> 0 | I19: =SUMIF('Bill Master List'!D:D,"Card14",'Bill Master List'!B:B) -> 0 | J19: =D19+I19 -> 0 | K19: =IF(C19>0,J19/C19,0) -> 0 | L19: =IF(C19=0,"Inactive",IF(K19<0.1,"✓ SAFE",IF(K19<0.3,"⚠ Warning",IF(K19<0.5,"🔶 CAUTION","🚨 DANGER")))) -> Inactive
A20: ='Credit Cards'!A17 -> Card15 | B20: ='Credit Cards'!B17 -> 0 | C20: ='Credit Cards'!C17 -> 0 | D20: ='Credit Cards'!H17 -> 0 | E20: =C20*0.3 -> 0 | F20: =MAX(E20-D20,0) -> 0 | G20: =C20*0.1 -> 0 | H20: =MAX(G20-D20,0) -> 0 | I20: =SUMIF('Bill Master List'!D:D,"Card15",'Bill Master List'!B:B) -> 0 | J20: =D20+I20 -> 0 | K20: =IF(C20>0,J20/C20,0) -> 0 | L20: =IF(C20=0,"Inactive",IF(K20<0.1,"✓ SAFE",IF(K20<0.3,"⚠ Warning",IF(K20<0.5,"🔶 CAUTION","🚨 DANGER")))) -> Inactive
A22: MONTHLY PAYMENT PLAN - Which Card Pays Which Bill
A23: Sorted by DUE DATE so you know what to pay FIRST each month
A24: # | B24: Bill Name | C24: Amount | D24: Due Day of Month | E24: Assigned Card | F24: Card Bank | G24: Card Due Day | H24: Card Report Day | I24: Late Fee If Missed | J24: Grace Period | K24: Consequence | L24: Priority
A25: 1 | B25: Storage 1 | C25: 570.6 | D25: Day 1 | E25: Card1 | F25: Navy Federal Card | G25: Day 10 | H25: Day 17 | I25: 40 | J25: 5 days | K25: Lien risk after 30 days late | L25: 🔴 HIGH
A26: 2 | B26: Groceries | C26: 400 | D26: Day 1 | E26: Card3 | F26: Indigo 1448 | G26: Day 20 | H26: Day 27 | I26: 0 | J26: None | K26: Variable expense - no late fee | L26: 🟢 LOW
A27: 3 | B27: Car Payment | C27: 785 | D27: Day 3 | E27: Card3 | F27: Indigo 1448 | G27: Day 20 | H27: Day 27 | I27: 39 | J27: 10 days | K27: Repo risk after 60+ days. Hits credit report at 30 days. | L27: 🔴 HIGH
A28: 4 | B28: Cell Phone | C28: 80 | D28: Day 5 | E28: Card3 | F28: Indigo 1448 | G28: Day 20 | H28: Day 27 | I28: 25 | J28: None | K28: Service disconnected after 30 days | L28: 🟡 MEDIUM
A29: 5 | B29: Storage 4 | C29: 98 | D29: Day 10 | E29: Card2 | F29: Indigo 3069 | G29: Day 15 | H29: Day 22 | I29: 20 | J29: 5 days | K29: Lien risk after 30 days late | L29: 🟢 LOW
A30: 6 | B30: Car Insurance | C30: 0 | D30: Day 10 | E30: Card1 | F30: Navy Federal Card | G30: Day 10 | H30: Day 17 | I30: 25 | J30: 10 days | K30: Policy cancellation after lapse | L30: 🔴 HIGH
A31: 7 | B31: Storage 2 | C31: 109 | D31: Day 12 | E31: Card1 | F31: Navy Federal Card | G31: Day 10 | H31: Day 17 | I31: 25 | J31: 5 days | K31: Lien risk after 30 days late | L31: 🟡 MEDIUM
A32: 8 | B32: Storage 3 | C32: 180 | D32: Day 15 | E32: Card2 | F32: Indigo 3069 | G32: Day 15 | H32: Day 22 | I32: 25 | J32: 5 days | K32: Lien risk after 30 days late | L32: 🟡 MEDIUM
A33: 9 | B33: Gas/Fuel | C33: 200 | D33: Day 15 | E33: Card4 | F33: Milestone 5093 | G33: Day 5 | H33: Day 12 | I33: 0 | J33: None | K33: Variable expense - no late fee | L33: 🟢 LOW
A34: 10 | B34: Klarna | C34: 45 | D34: Day 15 | E34: Card2 | F34: Indigo 3069 | G34: Day 15 | H34: Day 22 | I34: 25 | J34: None | K34: Hits credit after 30 days late | L34: 🟡 MEDIUM
A35: 11 | B35: NTTA | C35: 600 | D35: Day 15 | E35: Card5 | F35: Destiny 3992 | G35: Day 1 | H35: Day 7 | I35: 25 | J35: 30 days | K35: Can block vehicle registration. TxTag balance required. | L35: 🟡 MEDIUM
A36: 12 | B36: Intuit | C36: 75 | D36: Day 20 | E36: Card2 | F36: Indigo 3069 | G36: Day 15 | H36: Day 22 | I36: 0 | J36: None | K36: Service suspended if unpaid | L36: 🟢 LOW
A37: 13 | B37: Affirm | C37: 30 | D37: Day 20 | E37: Card5 | F37: Destiny 3992 | G37: Day 1 | H37: Day 7 | I37: 0 | J37: None | K37: No late fee but hits credit at 30 days | L37: 🟢 LOW
B39: TOTAL MONTHLY BILLS: | C39: =SUM(C25:C37) -> 3172.6 | H39: TOTAL LATE FEE EXPOSURE: | I39: =SUM(I25:I37) -> 249
A42: PER-CARD MONTHLY PAYMENT SUMMARY - What to Pay Each Card
A43: This is your ACTION LIST - Pay this amount to each card each month to cover all bills
A44: Card ID | B44: Bank | C44: Bills on This Card | D44: Total Monthly Charges | E44: Current Balance | F44: Balance After Charges | G44: Credit Limit | H44: Util After Charges | I44: Status | J44: Pay THIS to Card | K44: Target Balance After | L44: Target Util
A45: Card1 | B45: Navy Federal Card | C45: Storage 1, Car Insurance, Storage 2 | D45: 679.6 | E45: 1500.1 | F45: 2179.7 | G45: 1500 | H45: 1.4531333 | I45: 🚨 DANGER | J45: 2029.7 | K45: 150 | L45: 0.1
A46: Card2 | B46: Indigo 3069 | C46: Storage 4, Storage 3, Klarna, Intuit | D46: 398 | E46: 632.81 | F46: 1030.81 | G46: 500 | H46: 2.06162 | I46: 🚨 DANGER | J46: 980.81 | K46: 50 | L46: 0.1
A47: Card3 | B47: Indigo 1448 | C47: Groceries, Car Payment, Cell Phone | D47: 1265 | E47: 599.4 | F47: 1864.4 | G47: 1000 | H47: 1.8644 | I47: 🚨 DANGER | J47: 1764.4 | K47: 100 | L47: 0.1
A48: Card4 | B48: Milestone 5093 | C48: Gas/Fuel | D48: 200 | E48: 489.81 | F48: 689.81 | G48: 500 | H48: 1.37962 | I48: 🚨 DANGER | J48: 639.81 | K48: 50 | L48: 0.1
A49: Card5 | B49: Destiny 3992 | C49: NTTA, Affirm | D49: 630 | E49: 944.27 | F49: 1574.27 | G49: 1000 | H49: 1.57427 | I49: 🚨 DANGER | J49: 1474.27 | K49: 100 | L49: 0.1
I51: TOTAL TO PAY: | J51: 6888.99
A54: PAYMENT CALENDAR - When to Pay What (Sorted by Date)
A55: Your day-by-day payment schedule for each month
A56: Day | B56: What to Pay | C56: Amount | D56: Pay Using | E56: Bank | F56: Priority | G56: Late Fee | H56: Notes
A57: Day 1 | B57: 💳 Pay Storage 1 | C57: 570.6 | D57: Card1 | E57: Navy Federal Card | F57: 🔴 HIGH | G57: 40 | H57: Bill due. Lien risk after 30 days late
A58: Day 1 | B58: 💳 Pay Groceries | C58: 400 | D58: Card3 | E58: Indigo 1448 | F58: 🟢 LOW | H58: Bill due. Variable expense - no late fee
A59: Day 1 | B59: 🏦 PAY Card5 (Destiny 3992) | C59: 630 | D59: Bank Account | E59: Destiny 3992 | F59: 🔴 HIGH | G59: 40 | H59: Card payment due! Pay at least $630.00 for this month's bills. Late = interest + credit hit.
A60: Day 3 | B60: 💳 Pay Car Payment | C60: 785 | D60: Card3 | E60: Indigo 1448 | F60: 🔴 HIGH | G60: 39 | H60: Bill due. Repo risk after 60+ days. Hits credit report at 30 days.
A61: Day 5 | B61: 💳 Pay Cell Phone | C61: 80 | D61: Card3 | E61: Indigo 1448 | F61: 🟡 MEDIUM | G61: 25 | H61: Bill due. Service disconnected after 30 days
A62: Day 5 | B62: 🏦 PAY Card4 (Milestone 5093 ) | C62: 200 | D62: Bank Account | E62: Milestone 5093 | F62: 🔴 HIGH | G62: 40 | H62: Card payment due! Pay at least $200.00 for this month's bills. Late = interest + credit hit.
A63: Day 7 | B63: 📊 Card5 REPORTS TO BUREAUS | E63: Destiny 3992 | F63: ⚠️ KEY DATE | H63: Balance reported to credit bureaus! Pay DOWN Card5 BEFORE this date to lower reported utilization.
A64: Day 10 | B64: 💳 Pay Storage 4 | C64: 98 | D64: Card2 | E64: Indigo 3069 | F64: 🟢 LOW | G64: 20 | H64: Bill due. Lien risk after 30 days late
A65: Day 10 | B65: 💳 Pay Car Insurance | D65: Card1 | E65: Navy Federal Card | F65: 🔴 HIGH | G65: 25 | H65: Bill due. Policy cancellation after lapse
A66: Day 10 | B66: 🏦 PAY Card1 (Navy Federal Card) | C66: 679.6 | D66: Bank Account | E66: Navy Federal Card | F66: 🔴 HIGH | G66: 40 | H66: Card payment due! Pay at least $679.60 for this month's bills. Late = interest + credit hit.
A67: Day 12 | B67: 💳 Pay Storage 2 | C67: 109 | D67: Card1 | E67: Navy Federal Card | F67: 🟡 MEDIUM | G67: 25 | H67: Bill due. Lien risk after 30 days late
A68: Day 12 | B68: 📊 Card4 REPORTS TO BUREAUS | E68: Milestone 5093 | F68: ⚠️ KEY DATE | H68: Balance reported to credit bureaus! Pay DOWN Card4 BEFORE this date to lower reported utilization.
A69: Day 15 | B69: 💳 Pay Storage 3 | C69: 180 | D69: Card2 | E69: Indigo 3069 | F69: 🟡 MEDIUM | G69: 25 | H69: Bill due. Lien risk after 30 days late
A70: Day 15 | B70: 💳 Pay Gas/Fuel | C70: 200 | D70: Card4 | E70: Milestone 5093 | F70: 🟢 LOW | H70: Bill due. Variable expense - no late fee
A71: Day 15 | B71: 💳 Pay Klarna | C71: 45 | D71: Card2 | E71: Indigo 3069 | F71: 🟡 MEDIUM | G71: 25 | H71: Bill due. Hits credit after 30 days late
A72: Day 15 | B72: 💳 Pay NTTA | C72: 600 | D72: Card5 | E72: Destiny 3992 | F72: 🟡 MEDIUM | G72: 25 | H72: Bill due. Can block vehicle registration. TxTag balance required.
A73: Day 15 | B73: 🏦 PAY Card2 (Indigo 3069) | C73: 398 | D73: Bank Account | E73: Indigo 3069 | F73: 🔴 HIGH | G73: 40 | H73: Card payment due! Pay at least $398.00 for this month's bills. Late = interest + credit hit.
A74: Day 17 | B74: 📊 Card1 REPORTS TO BUREAUS | E74: Navy Federal Card | F74: ⚠️ KEY DATE | H74: Balance reported to credit bureaus! Pay DOWN Card1 BEFORE this date to lower reported utilization.
A75: Day 20 | B75: 💳 Pay Intuit | C75: 75 | D75: Card2 | E75: Indigo 3069 | F75: 🟢 LOW | H75: Bill due. Service suspended if unpaid
A76: Day 20 | B76: 💳 Pay Affirm | C76: 30 | D76: Card5 | E76: Destiny 3992 | F76: 🟢 LOW | H76: Bill due. No late fee but hits credit at 30 days
A77: Day 20 | B77: 🏦 PAY Card3 (Indigo 1448) | C77: 1265 | D77: Bank Account | E77: Indigo 1448 | F77: 🔴 HIGH | G77: 40 | H77: Card payment due! Pay at least $1265.00 for this month's bills. Late = interest + credit hit.
A78: Day 22 | B78: 📊 Card2 REPORTS TO BUREAUS | E78: Indigo 3069 | F78: ⚠️ KEY DATE | H78: Balance reported to credit bureaus! Pay DOWN Card2 BEFORE this date to lower reported utilization.
A79: Day 27 | B79: 📊 Card3 REPORTS TO BUREAUS | E79: Indigo 1448 | F79: ⚠️ KEY DATE | H79: Balance reported to credit bureaus! Pay DOWN Card3 BEFORE this date to lower reported utilization.

Sheet Card Payment Schedule
A1: CARD-BY-CARD PAYMENT SCHEDULE
A2: Shows exactly how much to pay on each card, each month
A4: Month | B4: Card1 Charges | C4: Card1 Payment | D4: Card1 Balance | E4: Card2 Charges | F4: Card2 Payment | G4: Card2 Balance | H4: Card3 Charges | I4: Card3 Payment | J4: Card3 Balance | K4: Card4 Charges | L4: Card4 Payment | M4: Card4 Balance | N4: Card5 Charges | O4: Card5 Payment | P4: Card5 Balance
A5: January
A6: February
A7: March
A8: April
A9: May
A10: June
A11: July
A12: August
A13: September
A14: October
A15: November
A16: December
... A24: • BALANCE = Previous Balance + New Charges + Interest - Payment
A25: PURCHASE INTEREST: | B25: =PurchaseBalance * (PurchaseAPR/12) -> #NAME?
A26: CASH ADVANCE INTEREST: | B26: =CashAdvanceBalance * (CashAdvanceAPR/12) -> #NAME?
A27: TOTAL INTEREST: | B27: =PurchaseInterest + CashAdvanceInterest -> #NAME?
A28: CASH ADVANCE FEE (if new CA): | B28: =NewCAAmount * CAFee% + CAFlatFee -> #NAME?

Sheet Payment Action List
A1: MONTHLY PAYMENT ACTION LIST
A2: Your monthly to-do list: Which card to pay, when, and how much
A4: January 2026 - PAYMENT CHECKLIST
A5: Card | B5: Bills Charged | C5: Total Charges | D5: Payment Due | E5: Due Date | F5: Status
A6: Card1 | B6: See 2026 Monthly Bills | E6: ='Credit Cards'!F3 -> 21 | F6: ☐ Paid
A7: Card2 | B7: See 2026 Monthly Bills | E7: ='Credit Cards'!F4 -> 8 | F7: ☐ Paid
A8: Card3 | B8: See 2026 Monthly Bills | E8: ='Credit Cards'!F5 -> 25 | F8: ☐ Paid
A9: Card4 | B9: See 2026 Monthly Bills | E9: ='Credit Cards'!F6 -> 8 | F9: ☐ Paid
A10: Card5 | B10: See 2026 Monthly Bills | E10: ='Credit Cards'!F7 -> 25 | F10: ☐ Paid
A11: MONTH TOTAL:
A13: February 2026 - PAYMENT CHECKLIST
A14: Card | B14: Bills Charged | C14: Total Charges | D14: Payment Due | E14: Due Date | F14: Status
A15: Card1 | B15: See 2026 Monthly Bills | E15: ='Credit Cards'!F3 -> 21 | F15: ☐ Paid
A16: Card2 | B16: See 2026 Monthly Bills | E16: ='Credit Cards'!F4 -> 8 | F16: ☐ Paid
A17: Card3 | B17: See 2026 Monthly Bills | E17: ='Credit Cards'!F5 -> 25 | F17: ☐ Paid
A18: Card4 | B18: See 2026 Monthly Bills | E18: ='Credit Cards'!F6 -> 8 | F18: ☐ Paid
A19: Card5 | B19: See 2026 Monthly Bills | E19: ='Credit Cards'!F7 -> 25 | F19: ☐ Paid
A20: MONTH TOTAL:
A22: March 2026 - PAYMENT CHECKLIST
A23: Card | B23: Bills Charged | C23: Total Charges | D23: Payment Due | E23: Due Date | F23: Status
A24: Card1 | B24: See 2026 Monthly Bills | E24: ='Credit Cards'!F3 -> 21 | F24: ☐ Paid
A25: Card2 | B25: See 2026 Monthly Bills | E25: ='Credit Cards'!F4 -> 8 | F25: ☐ Paid
A26: Card3 | B26: See 2026 Monthly Bills | E26: ='Credit Cards'!F5 -> 25 | F26: ☐ Paid
A27: Card4 | B27: See 2026 Monthly Bills | E27: ='Credit Cards'!F6 -> 8 | F27: ☐ Paid
A28: Card5 | B28: See 2026 Monthly Bills | E28: ='Credit Cards'!F7 -> 25 | F28: ☐ Paid
A29: MONTH TOTAL:
A31: April 2026 - PAYMENT CHECKLIST
A32: Card | B32: Bills Charged | C32: Total Charges | D32: Payment Due | E32: Due Date | F32: Status
A33: Card1 | B33: See 2026 Monthly Bills | E33: ='Credit Cards'!F3 -> 21 | F33: ☐ Paid
A34: Card2 | B34: See 2026 Monthly Bills | E34: ='Credit Cards'!F4 -> 8 | F34: ☐ Paid
A35: Card3 | B35: See 2026 Monthly Bills | E35: ='Credit Cards'!F5 -> 25 | F35: ☐ Paid
A36: Card4 | B36: See 2026 Monthly Bills | E36: ='Credit Cards'!F6 -> 8 | F36: ☐ Paid
A37: Card5 | B37: See 2026 Monthly Bills | E37: ='Credit Cards'!F7 -> 25 | F37: ☐ Paid
A38: MONTH TOTAL:
A40: May 2026 - PAYMENT CHECKLIST
A41: Card | B41: Bills Charged | C41: Total Charges | D41: Payment Due | E41: Due Date | F41: Status
A42: Card1 | B42: See 2026 Monthly Bills | E42: ='Credit Cards'!F3 -> 21 | F42: ☐ Paid
A43: Card2 | B43: See 2026 Monthly Bills | E43: ='Credit Cards'!F4 -> 8 | F43: ☐ Paid
A44: Card3 | B44: See 2026 Monthly Bills | E44: ='Credit Cards'!F5 -> 25 | F44: ☐ Paid
A45: Card4 | B45: See 2026 Monthly Bills | E45: ='Credit Cards'!F6 -> 8 | F45: ☐ Paid
A46: Card5 | B46: See 2026 Monthly Bills | E46: ='Credit Cards'!F7 -> 25 | F46: ☐ Paid
A47: MONTH TOTAL:
A49: June 2026 - PAYMENT CHECKLIST
A50: Card | B50: Bills Charged | C50: Total Charges | D50: Payment Due | E50: Due Date | F50: Status
A51: Card1 | B51: See 2026 Monthly Bills | E51: ='Credit Cards'!F3 -> 21 | F51: ☐ Paid
A52: Card2 | B52: See 2026 Monthly Bills | E52: ='Credit Cards'!F4 -> 8 | F52: ☐ Paid
A53: Card3 | B53: See 2026 Monthly Bills | E53: ='Credit Cards'!F5 -> 25 | F53: ☐ Paid
A54: Card4 | B54: See 2026 Monthly Bills | E54: ='Credit Cards'!F6 -> 8 | F54: ☐ Paid
A55: Card5 | B55: See 2026 Monthly Bills | E55: ='Credit Cards'!F7 -> 25 | F55: ☐ Paid
A56: MONTH TOTAL:
A58: July 2026 - PAYMENT CHECKLIST
A59: Card | B59: Bills Charged | C59: Total Charges | D59: Payment Due | E59: Due Date | F59: Status
A60: Card1 | B60: See 2026 Monthly Bills | E60: ='Credit Cards'!F3 -> 21 | F60: ☐ Paid
A61: Card2 | B61: See 2026 Monthly Bills | E61: ='Credit Cards'!F4 -> 8 | F61: ☐ Paid
A62: Card3 | B62: See 2026 Monthly Bills | E62: ='Credit Cards'!F5 -> 25 | F62: ☐ Paid
A63: Card4 | B63: See 2026 Monthly Bills | E63: ='Credit Cards'!F6 -> 8 | F63: ☐ Paid
A64: Card5 | B64: See 2026 Monthly Bills | E64: ='Credit Cards'!F7 -> 25 | F64: ☐ Paid
A65: MONTH TOTAL:
A67: August 2026 - PAYMENT CHECKLIST
A68: Card | B68: Bills Charged | C68: Total Charges | D68: Payment Due | E68: Due Date | F68: Status
A69: Card1 | B69: See 2026 Monthly Bills | E69: ='Credit Cards'!F3 -> 21 | F69: ☐ Paid
A70: Card2 | B70: See 2026 Monthly Bills | E70: ='Credit Cards'!F4 -> 8 | F70: ☐ Paid
A71: Card3 | B71: See 2026 Monthly Bills | E71: ='Credit Cards'!F5 -> 25 | F71: ☐ Paid
A72: Card4 | B72: See 2026 Monthly Bills | E72: ='Credit Cards'!F6 -> 8 | F72: ☐ Paid
A73: Card5 | B73: See 2026 Monthly Bills | E73: ='Credit Cards'!F7 -> 25 | F73: ☐ Paid
A74: MONTH TOTAL:
A76: September 2026 - PAYMENT CHECKLIST
A77: Card | B77: Bills Charged | C77: Total Charges | D77: Payment Due | E77: Due Date | F77: Status
A78: Card1 | B78: See 2026 Monthly Bills | E78: ='Credit Cards'!F3 -> 21 | F78: ☐ Paid
A79: Card2 | B79: See 2026 Monthly Bills | E79: ='Credit Cards'!F4 -> 8 | F79: ☐ Paid
A80: Card3 | B80: See 2026 Monthly Bills | E80: ='Credit Cards'!F5 -> 25 | F80: ☐ Paid
A81: Card4 | B81: See 2026 Monthly Bills | E81: ='Credit Cards'!F6 -> 8 | F81: ☐ Paid
A82: Card5 | B82: See 2026 Monthly Bills | E82: ='Credit Cards'!F7 -> 25 | F82: ☐ Paid
A83: MONTH TOTAL:
A85: October 2026 - PAYMENT CHECKLIST
A86: Card | B86: Bills Charged | C86: Total Charges | D86: Payment Due | E86: Due Date | F86: Status
A87: Card1 | B87: See 2026 Monthly Bills | E87: ='Credit Cards'!F3 -> 21 | F87: ☐ Paid
A88: Card2 | B88: See 2026 Monthly Bills | E88: ='Credit Cards'!F4 -> 8 | F88: ☐ Paid
A89: Card3 | B89: See 2026 Monthly Bills | E89: ='Credit Cards'!F5 -> 25 | F89: ☐ Paid
A90: Card4 | B90: See 2026 Monthly Bills | E90: ='Credit Cards'!F6 -> 8 | F90: ☐ Paid
A91: Card5 | B91: See 2026 Monthly Bills | E91: ='Credit Cards'!F7 -> 25 | F91: ☐ Paid
A92: MONTH TOTAL:
A94: November 2026 - PAYMENT CHECKLIST
A95: Card | B95: Bills Charged | C95: Total Charges | D95: Payment Due | E95: Due Date | F95: Status
A96: Card1 | B96: See 2026 Monthly Bills | E96: ='Credit Cards'!F3 -> 21 | F96: ☐ Paid
A97: Card2 | B97: See 2026 Monthly Bills | E97: ='Credit Cards'!F4 -> 8 | F97: ☐ Paid
A98: Card3 | B98: See 2026 Monthly Bills | E98: ='Credit Cards'!F5 -> 25 | F98: ☐ Paid
A99: Card4 | B99: See 2026 Monthly Bills | E99: ='Credit Cards'!F6 -> 8 | F99: ☐ Paid
A100: Card5 | B100: See 2026 Monthly Bills | E100: ='Credit Cards'!F7 -> 25 | F100: ☐ Paid
A101: MONTH TOTAL:
A103: December 2026 - PAYMENT CHECKLIST
A104: Card | B104: Bills Charged | C104: Total Charges | D104: Payment Due | E104: Due Date | F104: Status
A105: Card1 | B105: See 2026 Monthly Bills | E105: ='Credit Cards'!F3 -> 21 | F105: ☐ Paid
A106: Card2 | B106: See 2026 Monthly Bills | E106: ='Credit Cards'!F4 -> 8 | F106: ☐ Paid
A107: Card3 | B107: See 2026 Monthly Bills | E107: ='Credit Cards'!F5 -> 25 | F107: ☐ Paid
A108: Card4 | B108: See 2026 Monthly Bills | E108: ='Credit Cards'!F6 -> 8 | F108: ☐ Paid
A109: Card5 | B109: See 2026 Monthly Bills | E109: ='Credit Cards'!F7 -> 25 | F109: ☐ Paid
A110: MONTH TOTAL:

Sheet Card Summary
A1: CARD-BY-CARD SUMMARY
A2: Card ID | B2: Bank | C2: Current Balance | D2: Credit Limit | E2: Available Credit | F2: Utilization % | G2: APR | H2: Credit Report Day | I2: Monthly Bills Assigned | J2: Alert Status
A3: ='Credit Cards'!A3 -> Card1 | B3: ='Credit Cards'!B3 -> Navy Federal Card | C3: ='Credit Cards'!H3 -> 1500.1 | D3: ='Credit Cards'!C3 -> 1500 | E3: =D3-C3 -> -0.1 | F3: =IF(D3>0,C3/D3,0) -> 1.0000667 | G3: ='Credit Cards'!D3 -> 0.18 | H3: ='Credit Cards'!G3 -> 24 | I3: =SUMIF('Bill Master List'!D:D,"Card1",'Bill Master List'!B:B) -> 587 | J3: =IF(F3=0,"—",IF(F3<0.1,"✓ Safe",IF(F3<0.3,"⚠ Warning",IF(F3<0.5,"🔶 Caution","🚨 DANGER")))) -> 🚨 DANGER
A4: ='Credit Cards'!A4 -> Card2 | B4: ='Credit Cards'!B4 -> Indigo 3069 | C4: ='Credit Cards'!H4 -> 632.81 | D4: ='Credit Cards'!C4 -> 500 | E4: =D4-C4 -> -132.81 | F4: =IF(D4>0,C4/D4,0) -> 1.26562 | G4: ='Credit Cards'!D4 -> 0.359 | H4: ='Credit Cards'!G4 -> 9 | I4: =SUMIF('Bill Master List'!D:D,"Card2",'Bill Master List'!B:B) -> 398 | J4: =IF(F4=0,"—",IF(F4<0.1,"✓ Safe",IF(F4<0.3,"⚠ Warning",IF(F4<0.5,"🔶 Caution","🚨 DANGER")))) -> 🚨 DANGER
A5: ='Credit Cards'!A5 -> Card3 | B5: ='Credit Cards'!B5 -> Indigo 1448 | C5: ='Credit Cards'!H5 -> 599.4 | D5: ='Credit Cards'!C5 -> 1000 | E5: =D5-C5 -> 400.6 | F5: =IF(D5>0,C5/D5,0) -> 0.5994 | G5: ='Credit Cards'!D5 -> 0.359 | H5: ='Credit Cards'!G5 -> 26 | I5: =SUMIF('Bill Master List'!D:D,"Card3",'Bill Master List'!B:B) -> 1265 | J5: =IF(F5=0,"—",IF(F5<0.1,"✓ Safe",IF(F5<0.3,"⚠ Warning",IF(F5<0.5,"🔶 Caution","🚨 DANGER")))) -> 🚨 DANGER
A6: ='Credit Cards'!A6 -> Card4 | B6: ='Credit Cards'!B6 -> Milestone 5093 | C6: ='Credit Cards'!H6 -> 489.81 | D6: ='Credit Cards'!C6 -> 500 | E6: =D6-C6 -> 10.19 | F6: =IF(D6>0,C6/D6,0) -> 0.97962 | G6: ='Credit Cards'!D6 -> 0.359 | H6: ='Credit Cards'!G6 -> 9 | I6: =SUMIF('Bill Master List'!D:D,"Card4",'Bill Master List'!B:B) -> 200 | J6: =IF(F6=0,"—",IF(F6<0.1,"✓ Safe",IF(F6<0.3,"⚠ Warning",IF(F6<0.5,"🔶 Caution","🚨 DANGER")))) -> 🚨 DANGER
A7: ='Credit Cards'!A7 -> Card5 | B7: ='Credit Cards'!B7 -> Destiny 3992 | C7: ='Credit Cards'!H7 -> 944.27 | D7: ='Credit Cards'!C7 -> 1000 | E7: =D7-C7 -> 55.73 | F7: =IF(D7>0,C7/D7,0) -> 0.94427 | G7: ='Credit Cards'!D7 -> 0.359 | H7: ='Credit Cards'!G7 -> 26 | I7: =SUMIF('Bill Master List'!D:D,"Card5",'Bill Master List'!B:B) -> 630 | J7: =IF(F7=0,"—",IF(F7<0.1,"✓ Safe",IF(F7<0.3,"⚠ Warning",IF(F7<0.5,"🔶 Caution","🚨 DANGER")))) -> 🚨 DANGER
A8: ='Credit Cards'!A8 -> Card6 | B8: ='Credit Cards'!B8 -> 0 | C8: ='Credit Cards'!H8 -> 0 | D8: ='Credit Cards'!C8 -> 0 | E8: =D8-C8 -> 0 | F8: =IF(D8>0,C8/D8,0) -> 0 | G8: ='Credit Cards'!D8 -> 0 | H8: ='Credit Cards'!G8 -> 0 | I8: =SUMIF('Bill Master List'!D:D,"Card6",'Bill Master List'!B:B) -> 0 | J8: =IF(F8=0,"—",IF(F8<0.1,"✓ Safe",IF(F8<0.3,"⚠ Warning",IF(F8<0.5,"🔶 Caution","🚨 DANGER")))) -> —
A9: ='Credit Cards'!A9 -> Card7 | B9: ='Credit Cards'!B9 -> 0 | C9: ='Credit Cards'!H9 -> 0 | D9: ='Credit Cards'!C9 -> 0 | E9: =D9-C9 -> 0 | F9: =IF(D9>0,C9/D9,0) -> 0 | G9: ='Credit Cards'!D9 -> 0 | H9: ='Credit Cards'!G9 -> 0 | I9: =SUMIF('Bill Master List'!D:D,"Card7",'Bill Master List'!B:B) -> 0 | J9: =IF(F9=0,"—",IF(F9<0.1,"✓ Safe",IF(F9<0.3,"⚠ Warning",IF(F9<0.5,"🔶 Caution","🚨 DANGER")))) -> —
A10: ='Credit Cards'!A10 -> Card8 | B10: ='Credit Cards'!B10 -> 0 | C10: ='Credit Cards'!H10 -> 0 | D10: ='Credit Cards'!C10 -> 0 | E10: =D10-C10 -> 0 | F10: =IF(D10>0,C10/D10,0) -> 0 | G10: ='Credit Cards'!D10 -> 0 | H10: ='Credit Cards'!G10 -> 0 | I10: =SUMIF('Bill Master List'!D:D,"Card8",'Bill Master List'!B:B) -> 0 | J10: =IF(F10=0,"—",IF(F10<0.1,"✓ Safe",IF(F10<0.3,"⚠ Warning",IF(F10<0.5,"🔶 Caution","🚨 DANGER")))) -> —
A11: ='Credit Cards'!A11 -> Card9 | B11: ='Credit Cards'!B11 -> 0 | C11: ='Credit Cards'!H11 -> 0 | D11: ='Credit Cards'!C11 -> 0 | E11: =D11-C11 -> 0 | F11: =IF(D11>0,C11/D11,0) -> 0 | G11: ='Credit Cards'!D11 -> 0 | H11: ='Credit Cards'!G11 -> 0 | I11: =SUMIF('Bill Master List'!D:D,"Card9",'Bill Master List'!B:B) -> 0 | J11: =IF(F11=0,"—",IF(F11<0.1,"✓ Safe",IF(F11<0.3,"⚠ Warning",IF(F11<0.5,"🔶 Caution","🚨 DANGER")))) -> —
A12: ='Credit Cards'!A12 -> Card10 | B12: ='Credit Cards'!B12 -> 0 | C12: ='Credit Cards'!H12 -> 0 | D12: ='Credit Cards'!C12 -> 0 | E12: =D12-C12 -> 0 | F12: =IF(D12>0,C12/D12,0) -> 0 | G12: ='Credit Cards'!D12 -> 0 | H12: ='Credit Cards'!G12 -> 0 | I12: =SUMIF('Bill Master List'!D:D,"Card10",'Bill Master List'!B:B) -> 0 | J12: =IF(F12=0,"—",IF(F12<0.1,"✓ Safe",IF(F12<0.3,"⚠ Warning",IF(F12<0.5,"🔶 Caution","🚨 DANGER")))) -> —
A13: ='Credit Cards'!A13 -> Card11 | B13: ='Credit Cards'!B13 -> 0 | C13: ='Credit Cards'!H13 -> 0 | D13: ='Credit Cards'!C13 -> 0 | E13: =D13-C13 -> 0 | F13: =IF(D13>0,C13/D13,0) -> 0 | G13: ='Credit Cards'!D13 -> 0 | H13: ='Credit Cards'!G13 -> 0 | I13: =SUMIF('Bill Master List'!D:D,"Card11",'Bill Master List'!B:B) -> 0 | J13: =IF(F13=0,"—",IF(F13<0.1,"✓ Safe",IF(F13<0.3,"⚠ Warning",IF(F13<0.5,"🔶 Caution","🚨 DANGER")))) -> —
A14: ='Credit Cards'!A14 -> Card12 | B14: ='Credit Cards'!B14 -> 0 | C14: ='Credit Cards'!H14 -> 0 | D14: ='Credit Cards'!C14 -> 0 | E14: =D14-C14 -> 0 | F14: =IF(D14>0,C14/D14,0) -> 0 | G14: ='Credit Cards'!D14 -> 0 | H14: ='Credit Cards'!G14 -> 0 | I14: =SUMIF('Bill Master List'!D:D,"Card12",'Bill Master List'!B:B) -> 0 | J14: =IF(F14=0,"—",IF(F14<0.1,"✓ Safe",IF(F14<0.3,"⚠ Warning",IF(F14<0.5,"🔶 Caution","🚨 DANGER")))) -> —
A15: ='Credit Cards'!A15 -> Card13 | B15: ='Credit Cards'!B15 -> 0 | C15: ='Credit Cards'!H15 -> 0 | D15: ='Credit Cards'!C15 -> 0 | E15: =D15-C15 -> 0 | F15: =IF(D15>0,C15/D15,0) -> 0 | G15: ='Credit Cards'!D15 -> 0 | H15: ='Credit Cards'!G15 -> 0 | I15: =SUMIF('Bill Master List'!D:D,"Card13",'Bill Master List'!B:B) -> 0 | J15: =IF(F15=0,"—",IF(F15<0.1,"✓ Safe",IF(F15<0.3,"⚠ Warning",IF(F15<0.5,"🔶 Caution","🚨 DANGER")))) -> —
A16: ='Credit Cards'!A16 -> Card14 | B16: ='Credit Cards'!B16 -> 0 | C16: ='Credit Cards'!H16 -> 0 | D16: ='Credit Cards'!C16 -> 0 | E16: =D16-C16 -> 0 | F16: =IF(D16>0,C16/D16,0) -> 0 | G16: ='Credit Cards'!D16 -> 0 | H16: ='Credit Cards'!G16 -> 0 | I16: =SUMIF('Bill Master List'!D:D,"Card14",'Bill Master List'!B:B) -> 0 | J16: =IF(F16=0,"—",IF(F16<0.1,"✓ Safe",IF(F16<0.3,"⚠ Warning",IF(F16<0.5,"🔶 Caution","🚨 DANGER")))) -> —
A17: ='Credit Cards'!A17 -> Card15 | B17: ='Credit Cards'!B17 -> 0 | C17: ='Credit Cards'!H17 -> 0 | D17: ='Credit Cards'!C17 -> 0 | E17: =D17-C17 -> 0 | F17: =IF(D17>0,C17/D17,0) -> 0 | G17: ='Credit Cards'!D17 -> 0 | H17: ='Credit Cards'!G17 -> 0 | I17: =SUMIF('Bill Master List'!D:D,"Card15",'Bill Master List'!B:B) -> 0 | J17: =IF(F17=0,"—",IF(F17<0.1,"✓ Safe",IF(F17<0.3,"⚠ Warning",IF(F17<0.5,"🔶 Caution","🚨 DANGER")))) -> —
A18: TOTALS | C18: =SUM(C3:C17) -> 4166.39 | D18: =SUM(D3:D17) -> 4500 | E18: =SUM(E3:E17) -> 333.61 | I18: =SUM(I3:I17) -> 3080

Sheet Cash Advance Calculator
A1: CASH ADVANCE INTEREST & FEE CALCULATOR
A3: This sheet shows daily interest accumulation on cash advances.
A4: Cash advances accrue interest DAILY from day 1 (no grace period).
A6: Card | B6: CA Balance | C6: CA APR | D6: Daily Rate | E6: Daily Interest | F6: Monthly Interest (30 days) | G6: CA Fee % | H6: Flat Fee
A7: ='Credit Cards'!A3 -> Card1 | B7: ='Credit Cards'!L3 -> 0 | C7: ='Credit Cards'!N3 -> 18 | D7: =C7/365 -> 0.049315068 | E7: =B7*D7 -> 0 | F7: =E7*30 -> 0 | G7: ='Credit Cards'!O3 -> 0.05 | H7: ='Credit Cards'!P3 -> 10
A8: ='Credit Cards'!A4 -> Card2 | B8: ='Credit Cards'!L4 -> 0 | C8: ='Credit Cards'!N4 -> 35.9 | D8: =C8/365 -> 0.098356164 | E8: =B8*D8 -> 0 | F8: =E8*30 -> 0 | G8: ='Credit Cards'!O4 -> 0.05 | H8: ='Credit Cards'!P4 -> 10
A9: ='Credit Cards'!A5 -> Card3 | B9: ='Credit Cards'!L5 -> 100 | C9: ='Credit Cards'!N5 -> 35.9 | D9: =C9/365 -> 0.098356164 | E9: =B9*D9 -> 9.8356164 | F9: =E9*30 -> 295.06849 | G9: ='Credit Cards'!O5 -> 0.05 | H9: ='Credit Cards'!P5 -> 10
A10: ='Credit Cards'!A6 -> Card4 | B10: ='Credit Cards'!L6 -> 0 | C10: ='Credit Cards'!N6 -> 35.9 | D10: =C10/365 -> 0.098356164 | E10: =B10*D10 -> 0 | F10: =E10*30 -> 0 | G10: ='Credit Cards'!O6 -> 0.05 | H10: ='Credit Cards'!P6 -> 10
A11: ='Credit Cards'!A7 -> Card5 | B11: ='Credit Cards'!L7 -> 100 | C11: ='Credit Cards'!N7 -> 35.9 | D11: =C11/365 -> 0.098356164 | E11: =B11*D11 -> 9.8356164 | F11: =E11*30 -> 295.06849 | G11: ='Credit Cards'!O7 -> 0.05 | H11: ='Credit Cards'!P7 -> 10
A12: ='Credit Cards'!A8 -> Card6 | B12: ='Credit Cards'!L8 -> 0 | C12: ='Credit Cards'!N8 -> 0 | D12: =C12/365 -> 0 | E12: =B12*D12 -> 0 | F12: =E12*30 -> 0 | G12: ='Credit Cards'!O8 -> 0 | H12: ='Credit Cards'!P8 -> 0
A13: ='Credit Cards'!A9 -> Card7 | B13: ='Credit Cards'!L9 -> 0 | C13: ='Credit Cards'!N9 -> 0 | D13: =C13/365 -> 0 | E13: =B13*D13 -> 0 | F13: =E13*30 -> 0 | G13: ='Credit Cards'!O9 -> 0 | H13: ='Credit Cards'!P9 -> 0
A14: ='Credit Cards'!A10 -> Card8 | B14: ='Credit Cards'!L10 -> 0 | C14: ='Credit Cards'!N10 -> 0 | D14: =C14/365 -> 0 | E14: =B14*D14 -> 0 | F14: =E14*30 -> 0 | G14: ='Credit Cards'!O10 -> 0 | H14: ='Credit Cards'!P10 -> 0
A15: ='Credit Cards'!A11 -> Card9 | B15: ='Credit Cards'!L11 -> 0 | C15: ='Credit Cards'!N11 -> 0 | D15: =C15/365 -> 0 | E15: =B15*D15 -> 0 | F15: =E15*30 -> 0 | G15: ='Credit Cards'!O11 -> 0 | H15: ='Credit Cards'!P11 -> 0
A16: ='Credit Cards'!A12 -> Card10 | B16: ='Credit Cards'!L12 -> 0 | C16: ='Credit Cards'!N12 -> 0 | D16: =C16/365 -> 0 | E16: =B16*D16 -> 0 | F16: =E16*30 -> 0 | G16: ='Credit Cards'!O12 -> 0 | H16: ='Credit Cards'!P12 -> 0
A17: ='Credit Cards'!A13 -> Card11 | B17: ='Credit Cards'!L13 -> 0 | C17: ='Credit Cards'!N13 -> 0 | D17: =C17/365 -> 0 | E17: =B17*D17 -> 0 | F17: =E17*30 -> 0 | G17: ='Credit Cards'!O13 -> 0 | H17: ='Credit Cards'!P13 -> 0
A18: ='Credit Cards'!A14 -> Card12 | B18: ='Credit Cards'!L14 -> 0 | C18: ='Credit Cards'!N14 -> 0 | D18: =C18/365 -> 0 | E18: =B18*D18 -> 0 | F18: =E18*30 -> 0 | G18: ='Credit Cards'!O14 -> 0 | H18: ='Credit Cards'!P14 -> 0
... A21: ='Credit Cards'!A17 -> Card15 | B21: ='Credit Cards'!L17 -> 0 | C21: ='Credit Cards'!N17 -> 0 | D21: =C21/365 -> 0 | E21: =B21*D21 -> 0 | F21: =E21*30 -> 0 | G21: ='Credit Cards'!O17 -> 0 | H21: ='Credit Cards'!P17 -> 0
A22: TOTAL | B22: =SUM(B7:B21) -> 200 | E22: =SUM(E7:E21) -> 19.671233 | F22: =SUM(F7:F21) -> 590.13699

Sheet Card Strategy
A1: 🎯 PLATINUM CARD STRATEGY CENTER
A2: Real-time tactical recommendations per card
A4: Card | B4: Bank | C4: Utilization % | D4: Monthly Bills | E4: CA Balance | F4: Danger Level | G4: Strategy
A5: ='Credit Cards'!A3 -> Card1 | B5: ='Credit Cards'!B3 -> Navy Federal Card | C5: ='Credit Cards'!M3/'Credit Cards'!C3 -> 1.0000667 | D5: =SUMIF('Bill Master List'!D:D,A5,'Bill Master List'!B:B) -> 587 | E5: ='Credit Cards'!L3 -> 0 | F5: =IF(E5>0,"🚨 DANGER",IF(C5>=0.5,"🚨 DANGER",IF(C5>=0.3,"🔶 CAUTION",IF(C5>=0.1,"⚠ Warning","✓ SAFE")))) -> 🚨 DANGER | G5: =IF(OR(F5="🚨 DANGER",E5>0),"Phase 1: Stop all new charges. Pay before report day to get under 50%. Clear cash advances within 1-2 cycles.",IF(F5="🔶 CAUTION","Phase 1: Freeze non-essential spending. Get under 30% before report day. Reassign flexible bills.",IF(F5="⚠ Warning","Controlled float: Keep 5-10% util. Pay strategically before report day.","Safe zone: Use for small essentials, pay in full before report day."))) -> Phase 1: Stop all new charges. Pay before report day to get under 50%. Clear cash advances within 1-2 cycles.
A6: ='Credit Cards'!A4 -> Card2 | B6: ='Credit Cards'!B4 -> Indigo 3069 | C6: ='Credit Cards'!M4/'Credit Cards'!C4 -> 1.26562 | D6: =SUMIF('Bill Master List'!D:D,A6,'Bill Master List'!B:B) -> 398 | E6: ='Credit Cards'!L4 -> 0 | F6: =IF(E6>0,"🚨 DANGER",IF(C6>=0.5,"🚨 DANGER",IF(C6>=0.3,"🔶 CAUTION",IF(C6>=0.1,"⚠ Warning","✓ SAFE")))) -> 🚨 DANGER | G6: =IF(OR(F6="🚨 DANGER",E6>0),"Phase 1: Stop all new charges. Pay before report day to get under 50%. Clear cash advances within 1-2 cycles.",IF(F6="🔶 CAUTION","Phase 1: Freeze non-essential spending. Get under 30% before report day. Reassign flexible bills.",IF(F6="⚠ Warning","Controlled float: Keep 5-10% util. Pay strategically before report day.","Safe zone: Use for small essentials, pay in full before report day."))) -> Phase 1: Stop all new charges. Pay before report day to get under 50%. Clear cash advances within 1-2 cycles.
A7: ='Credit Cards'!A5 -> Card3 | B7: ='Credit Cards'!B5 -> Indigo 1448 | C7: ='Credit Cards'!M5/'Credit Cards'!C5 -> 0.54797 | D7: =SUMIF('Bill Master List'!D:D,A7,'Bill Master List'!B:B) -> 1265 | E7: ='Credit Cards'!L5 -> 100 | F7: =IF(E7>0,"🚨 DANGER",IF(C7>=0.5,"🚨 DANGER",IF(C7>=0.3,"🔶 CAUTION",IF(C7>=0.1,"⚠ Warning","✓ SAFE")))) -> 🚨 DANGER | G7: =IF(OR(F7="🚨 DANGER",E7>0),"Phase 1: Stop all new charges. Pay before report day to get under 50%. Clear cash advances within 1-2 cycles.",IF(F7="🔶 CAUTION","Phase 1: Freeze non-essential spending. Get under 30% before report day. Reassign flexible bills.",IF(F7="⚠ Warning","Controlled float: Keep 5-10% util. Pay strategically before report day.","Safe zone: Use for small essentials, pay in full before report day."))) -> Phase 1: Stop all new charges. Pay before report day to get under 50%. Clear cash advances within 1-2 cycles.
A8: ='Credit Cards'!A6 -> Card4 | B8: ='Credit Cards'!B6 -> Milestone 5093 | C8: ='Credit Cards'!M6/'Credit Cards'!C6 -> 0.97962 | D8: =SUMIF('Bill Master List'!D:D,A8,'Bill Master List'!B:B) -> 200 | E8: ='Credit Cards'!L6 -> 0 | F8: =IF(E8>0,"🚨 DANGER",IF(C8>=0.5,"🚨 DANGER",IF(C8>=0.3,"🔶 CAUTION",IF(C8>=0.1,"⚠ Warning","✓ SAFE")))) -> 🚨 DANGER | G8: =IF(OR(F8="🚨 DANGER",E8>0),"Phase 1: Stop all new charges. Pay before report day to get under 50%. Clear cash advances within 1-2 cycles.",IF(F8="🔶 CAUTION","Phase 1: Freeze non-essential spending. Get under 30% before report day. Reassign flexible bills.",IF(F8="⚠ Warning","Controlled float: Keep 5-10% util. Pay strategically before report day.","Safe zone: Use for small essentials, pay in full before report day."))) -> Phase 1: Stop all new charges. Pay before report day to get under 50%. Clear cash advances within 1-2 cycles.
A9: ='Credit Cards'!A7 -> Card5 | B9: ='Credit Cards'!B7 -> Destiny 3992 | C9: ='Credit Cards'!M7/'Credit Cards'!C7 -> 0.95834 | D9: =SUMIF('Bill Master List'!D:D,A9,'Bill Master List'!B:B) -> 630 | E9: ='Credit Cards'!L7 -> 100 | F9: =IF(E9>0,"🚨 DANGER",IF(C9>=0.5,"🚨 DANGER",IF(C9>=0.3,"🔶 CAUTION",IF(C9>=0.1,"⚠ Warning","✓ SAFE")))) -> 🚨 DANGER | G9: =IF(OR(F9="🚨 DANGER",E9>0),"Phase 1: Stop all new charges. Pay before report day to get under 50%. Clear cash advances within 1-2 cycles.",IF(F9="🔶 CAUTION","Phase 1: Freeze non-essential spending. Get under 30% before report day. Reassign flexible bills.",IF(F9="⚠ Warning","Controlled float: Keep 5-10% util. Pay strategically before report day.","Safe zone: Use for small essentials, pay in full before report day."))) -> Phase 1: Stop all new charges. Pay before report day to get under 50%. Clear cash advances within 1-2 cycles.
